{"5":{"url":"http:\/\/elections.interieur.gouv.fr\/MN2014\/006\/index.html","libelle":"06 - ALPES MARITIMES","ListeVilles":{"1":{"url":"http:\/\/elections.interieur.gouv.fr\/MN2014\/006\/006A.html","libelle":"A","villes":{"1":{"nom":"Aiglun","Listes":{"libelle":"Candidats (Scrutin majoritaire)","url":"http:\/\/elections.interieur.gouv.fr\/MN2014\/006\/C1006001.html"},"resultat":{"libelle":"R&eacute;sultats re&ccedil;us 1er tour","url":"http:\/\/elections.interieur.gouv.fr\/MN2014\/006\/006001.html"}},"2":{"nom":"Amirat","Listes":{"libelle":"Candidats (Scrutin majoritaire)","url":"http:\/\/elections.interieur.gouv.fr\/MN2014\/006\/C1006002.html"},"resultat":{"libelle":"R&eacute;sultats re&ccedil;us 1er tour","url":"http:\/\/elections.interieur.gouv.fr\/MN2014\/006\/006002.html"}},"3":{"nom":"Andon","Listes":{"libelle":"Candidats (Scrutin majoritaire)","url":"http:\/\/elections.interieur.gouv.fr\/MN2014\/006\/C1006003.html"},"resultat":{"libelle":"R&eacute;sultats re&ccedil;us 1er tour","url":"http:\/\/elections.interieur.gouv.fr\/MN2014\/006\/006003.html"}},"4":{"nom":"Antibes","Listes":{"libelle":"Listes","url":"http:\/\/elections.interieur.gouv.fr\/MN2014\/006\/C1006004.html"},"resultat":{"libelle":"R&eacute;sultats re&ccedil;us 1er tour","url":"http:\/\/elections.interieur.gouv.fr\/MN2014\/006\/006004.html"}},"5":{"nom":"Ascros","Listes":{"libelle":"Candidats (Scrutin majoritaire)","url":"http:\/\/elections.interieur.gouv.fr\/MN2014\/006\/C1006005.html"},"resultat":{"libelle":"R&eacute;sultats re&ccedil;us 1er tour","url":"http:\/\/elections.interieur.gouv.fr\/MN2014\/006\/006005.html"}},"6":{"nom":"Aspremont","Listes":{"libelle":"Listes","url":"http:\/\/elections.interieur.gouv.fr\/MN2014\/006\/C1006006.html"},"resultat":{"libelle":"R&eacute;sultats re&ccedil;us 1er tour","url":"http:\/\/elections.interieur.gouv.fr\/MN2014\/006\/006006.html"}},"7":{"nom":"Auribeau-Sur-Siagne","Listes":{"libelle":"Listes","url":"http:\/\/elections.interieur.gouv.fr\/MN2014\/006\/C1006007.html"},"resultat":{"libelle":"R&eacute;sultats re&ccedil;us 1er tour","url":"http:\/\/elections.interieur.gouv.fr\/MN2014\/006\/006007.html"}},"8":{"nom":"Auvare","Listes":{"libelle":"Candidats (Scrutin majoritaire)","url":"http:\/\/elections.interieur.gouv.fr\/MN2014\/006\/C1006008.html"},"resultat":{"libelle":"R&eacute;sultats re&ccedil;us 1er tour","url":"http:\/\/elections.interieur.gouv.fr\/MN2014\/006\/006008.html"}}}},"2":{"url":"http:\/\/elections.interieur.gouv.fr\/MN2014\/006\/006B.html","libelle":"B","villes":{"1":{"nom":"Bairols","Listes":{"libelle":"Candidats (Scrutin majoritaire)","url":"http:\/\/elections.interieur.gouv.fr\/MN2014\/006\/C1006009.html"},"resultat":{"libelle":"R&eacute;sultats re&ccedil;us 1er tour","url":"http:\/\/elections.interieur.gouv.fr\/MN2014\/006\/006009.html"}},"2":{"nom":"Beaulieu-Sur-Mer","Listes":{"libelle":"Listes","url":"http:\/\/elections.interieur.gouv.fr\/MN2014\/006\/C1006011.html"},"resultat":{"libelle":"R&eacute;sultats re&ccedil;us 1er tour","url":"http:\/\/elections.interieur.gouv.fr\/MN2014\/006\/006011.html"}},"3":{"nom":"Beausoleil","Listes":{"libelle":"Listes","url":"http:\/\/elections.interieur.gouv.fr\/MN2014\/006\/C1006012.html"},"resultat":{"libelle":"R&eacute;sultats re&ccedil;us 1er tour","url":"http:\/\/elections.interieur.gouv.fr\/MN2014\/006\/006012.html"}},"4":{"nom":"Belv&eacute;d&egrave;re","Listes":{"libelle":"Candidats (Scrutin majoritaire)","url":"http:\/\/elections.interieur.gouv.fr\/MN2014\/006\/C1006013.html"},"resultat":{"libelle":"R&eacute;sultats re&ccedil;us 1er tour","url":"http:\/\/elections.interieur.gouv.fr\/MN2014\/006\/006013.html"}},"5":{"nom":"Bendejun","Listes":{"libelle":"Candidats (Scrutin majoritaire)","url":"http:\/\/elections.interieur.gouv.fr\/MN2014\/006\/C1006014.html"},"resultat":{"libelle":"R&eacute;sultats re&ccedil;us 1er tour","url":"http:\/\/elections.interieur.gouv.fr\/MN2014\/006\/006014.html"}},"6":{"nom":"Berre-Les-Alpes","Listes":{"libelle":"Listes","url":"http:\/\/elections.interieur.gouv.fr\/MN2014\/006\/C1006015.html"},"resultat":{"libelle":"R&eacute;sultats re&ccedil;us 1er tour","url":"http:\/\/elections.interieur.gouv.fr\/MN2014\/006\/006015.html"}},"7":{"nom":"Beuil","Listes":{"libelle":"Candidats (Scrutin majoritaire)","url":"http:\/\/elections.interieur.gouv.fr\/MN2014\/006\/C1006016.html"},"resultat":{"libelle":"R&eacute;sultats re&ccedil;us 1er tour","url":"http:\/\/elections.interieur.gouv.fr\/MN2014\/006\/006016.html"}},"8":{"nom":"B&eacute;zaudun-Les-Alpes","Listes":{"libelle":"Candidats (Scrutin majoritaire)","url":"http:\/\/elections.interieur.gouv.fr\/MN2014\/006\/C1006017.html"},"resultat":{"libelle":"R&eacute;sultats re&ccedil;us 1er tour","url":"http:\/\/elections.interieur.gouv.fr\/MN2014\/006\/006017.html"}},"9":{"nom":"Biot","Listes":{"libelle":"Listes","url":"http:\/\/elections.interieur.gouv.fr\/MN2014\/006\/C1006018.html"},"resultat":{"libelle":"R&eacute;sultats re&ccedil;us 1er tour","url":"http:\/\/elections.interieur.gouv.fr\/MN2014\/006\/006018.html"}},"10":{"nom":"Blausasc","Listes":{"libelle":"Listes","url":"http:\/\/elections.interieur.gouv.fr\/MN2014\/006\/C1006019.html"},"resultat":{"libelle":"R&eacute;sultats re&ccedil;us 1er tour","url":"http:\/\/elections.interieur.gouv.fr\/MN2014\/006\/006019.html"}},"11":{"nom":"Bonson","Listes":{"libelle":"Candidats (Scrutin majoritaire)","url":"http:\/\/elections.interieur.gouv.fr\/MN2014\/006\/C1006021.html"},"resultat":{"libelle":"R&eacute;sultats re&ccedil;us 1er tour","url":"http:\/\/elections.interieur.gouv.fr\/MN2014\/006\/006021.html"}},"12":{"nom":"Bouyon","Listes":{"libelle":"Candidats (Scrutin majoritaire)","url":"http:\/\/elections.interieur.gouv.fr\/MN2014\/006\/C1006022.html"},"resultat":{"libelle":"R&eacute;sultats re&ccedil;us 1er tour","url":"http:\/\/elections.interieur.gouv.fr\/MN2014\/006\/006022.html"}},"13":{"nom":"Breil-Sur-Roya","Listes":{"libelle":"Listes","url":"http:\/\/elections.interieur.gouv.fr\/MN2014\/006\/C1006023.html"},"resultat":{"libelle":"R&eacute;sultats re&ccedil;us 1er tour","url":"http:\/\/elections.interieur.gouv.fr\/MN2014\/006\/006023.html"}},"14":{"nom":"Brian&ccedil;onnet","Listes":{"libelle":"Candidats (Scrutin majoritaire)","url":"http:\/\/elections.interieur.gouv.fr\/MN2014\/006\/C1006024.html"},"resultat":{"libelle":"R&eacute;sultats re&ccedil;us 1er tour","url":"http:\/\/elections.interieur.gouv.fr\/MN2014\/006\/006024.html"}}}},"3":{"url":"http:\/\/elections.interieur.gouv.fr\/MN2014\/006\/006C.html","libelle":"C","villes":{"1":{"nom":"Cabris","Listes":{"libelle":"Listes","url":"http:\/\/elections.interieur.gouv.fr\/MN2014\/006\/C1006026.html"},"resultat":{"libelle":"R&eacute;sultats re&ccedil;us 1er tour","url":"http:\/\/elections.interieur.gouv.fr\/MN2014\/006\/006026.html"}},"2":{"nom":"Cagnes-Sur-Mer","Listes":{"libelle":"Listes","url":"http:\/\/elections.interieur.gouv.fr\/MN2014\/006\/C1006027.html"},"resultat":{"libelle":"R&eacute;sultats re&ccedil;us 1er tour","url":"http:\/\/elections.interieur.gouv.fr\/MN2014\/006\/006027.html"}},"3":{"nom":"Caille","Listes":{"libelle":"Candidats (Scrutin majoritaire)","url":"http:\/\/elections.interieur.gouv.fr\/MN2014\/006\/C1006028.html"},"resultat":{"libelle":"R&eacute;sultats re&ccedil;us 1er tour","url":"http:\/\/elections.interieur.gouv.fr\/MN2014\/006\/006028.html"}},"4":{"nom":"Cannes","Listes":{"libelle":"Listes","url":"http:\/\/elections.interieur.gouv.fr\/MN2014\/006\/C1006029.html"},"resultat":{"libelle":"R&eacute;sultats re&ccedil;us 1er tour","url":"http:\/\/elections.interieur.gouv.fr\/MN2014\/006\/006029.html"}},"5":{"nom":"Cantaron","Listes":{"libelle":"Listes","url":"http:\/\/elections.interieur.gouv.fr\/MN2014\/006\/C1006031.html"},"resultat":{"libelle":"R&eacute;sultats re&ccedil;us 1er tour","url":"http:\/\/elections.interieur.gouv.fr\/MN2014\/006\/006031.html"}},"6":{"nom":"Cap-D'Ail","Listes":{"libelle":"Listes","url":"http:\/\/elections.interieur.gouv.fr\/MN2014\/006\/C1006032.html"},"resultat":{"libelle":"R&eacute;sultats re&ccedil;us 1er tour","url":"http:\/\/elections.interieur.gouv.fr\/MN2014\/006\/006032.html"}},"7":{"nom":"Carros","Listes":{"libelle":"Listes","url":"http:\/\/elections.interieur.gouv.fr\/MN2014\/006\/C1006033.html"},"resultat":{"libelle":"R&eacute;sultats re&ccedil;us 1er tour","url":"http:\/\/elections.interieur.gouv.fr\/MN2014\/006\/006033.html"}},"8":{"nom":"Castagniers","Listes":{"libelle":"Listes","url":"http:\/\/elections.interieur.gouv.fr\/MN2014\/006\/C1006034.html"},"resultat":{"libelle":"R&eacute;sultats re&ccedil;us 1er tour","url":"http:\/\/elections.interieur.gouv.fr\/MN2014\/006\/006034.html"}},"9":{"nom":"Castellar","Listes":{"libelle":"Candidats (Scrutin majoritaire)","url":"http:\/\/elections.interieur.gouv.fr\/MN2014\/006\/C1006035.html"},"resultat":{"libelle":"R&eacute;sultats re&ccedil;us 1er tour","url":"http:\/\/elections.interieur.gouv.fr\/MN2014\/006\/006035.html"}},"10":{"nom":"Castillon","Listes":{"libelle":"Candidats (Scrutin majoritaire)","url":"http:\/\/elections.interieur.gouv.fr\/MN2014\/006\/C1006036.html"},"resultat":{"libelle":"R&eacute;sultats re&ccedil;us 1er tour","url":"http:\/\/elections.interieur.gouv.fr\/MN2014\/006\/006036.html"}},"11":{"nom":"Caussols","Listes":{"libelle":"Candidats (Scrutin majoritaire)","url":"http:\/\/elections.interieur.gouv.fr\/MN2014\/006\/C1006037.html"},"resultat":{"libelle":"R&eacute;sultats re&ccedil;us 1er tour","url":"http:\/\/elections.interieur.gouv.fr\/MN2014\/006\/006037.html"}},"12":{"nom":"Ch&acirc;teauneuf-D'Entraunes","Listes":{"libelle":"Candidats (Scrutin majoritaire)","url":"http:\/\/elections.interieur.gouv.fr\/MN2014\/006\/C1006040.html"},"resultat":{"libelle":"R&eacute;sultats re&ccedil;us 1er tour","url":"http:\/\/elections.interieur.gouv.fr\/MN2014\/006\/006040.html"}},"13":{"nom":"Ch&acirc;teauneuf-Grasse","Listes":{"libelle":"Listes","url":"http:\/\/elections.interieur.gouv.fr\/MN2014\/006\/C1006038.html"},"resultat":{"libelle":"R&eacute;sultats re&ccedil;us 1er tour","url":"http:\/\/elections.interieur.gouv.fr\/MN2014\/006\/006038.html"}},"14":{"nom":"Ch&acirc;teauneuf-Villevieille","Listes":{"libelle":"Candidats (Scrutin majoritaire)","url":"http:\/\/elections.interieur.gouv.fr\/MN2014\/006\/C1006039.html"},"resultat":{"libelle":"R&eacute;sultats re&ccedil;us 1er tour","url":"http:\/\/elections.interieur.gouv.fr\/MN2014\/006\/006039.html"}},"15":{"nom":"Cipi&egrave;res","Listes":{"libelle":"Candidats (Scrutin majoritaire)","url":"http:\/\/elections.interieur.gouv.fr\/MN2014\/006\/C1006041.html"},"resultat":{"libelle":"R&eacute;sultats re&ccedil;us 1er tour","url":"http:\/\/elections.interieur.gouv.fr\/MN2014\/006\/006041.html"}},"16":{"nom":"Clans","Listes":{"libelle":"Candidats (Scrutin majoritaire)","url":"http:\/\/elections.interieur.gouv.fr\/MN2014\/006\/C1006042.html"},"resultat":{"libelle":"R&eacute;sultats re&ccedil;us 1er tour","url":"http:\/\/elections.interieur.gouv.fr\/MN2014\/006\/006042.html"}},"17":{"nom":"Coaraze","Listes":{"libelle":"Candidats (Scrutin majoritaire)","url":"http:\/\/elections.interieur.gouv.fr\/MN2014\/006\/C1006043.html"},"resultat":{"libelle":"R&eacute;sultats re&ccedil;us 1er tour","url":"http:\/\/elections.interieur.gouv.fr\/MN2014\/006\/006043.html"}},"18":{"nom":"Collongues","Listes":{"libelle":"Candidats (Scrutin majoritaire)","url":"http:\/\/elections.interieur.gouv.fr\/MN2014\/006\/C1006045.html"},"resultat":{"libelle":"R&eacute;sultats re&ccedil;us 1er tour","url":"http:\/\/elections.interieur.gouv.fr\/MN2014\/006\/006045.html"}},"19":{"nom":"Colomars","Listes":{"libelle":"Listes","url":"http:\/\/elections.interieur.gouv.fr\/MN2014\/006\/C1006046.html"},"resultat":{"libelle":"R&eacute;sultats re&ccedil;us 1er tour","url":"http:\/\/elections.interieur.gouv.fr\/MN2014\/006\/006046.html"}},"20":{"nom":"Cons&eacute;gudes","Listes":{"libelle":"Candidats (Scrutin majoritaire)","url":"http:\/\/elections.interieur.gouv.fr\/MN2014\/006\/C1006047.html"},"resultat":{"libelle":"R&eacute;sultats re&ccedil;us 1er tour","url":"http:\/\/elections.interieur.gouv.fr\/MN2014\/006\/006047.html"}},"21":{"nom":"Contes","Listes":{"libelle":"Listes","url":"http:\/\/elections.interieur.gouv.fr\/MN2014\/006\/C1006048.html"},"resultat":{"libelle":"R&eacute;sultats re&ccedil;us 1er tour","url":"http:\/\/elections.interieur.gouv.fr\/MN2014\/006\/006048.html"}},"22":{"nom":"Courmes","Listes":{"libelle":"Candidats (Scrutin majoritaire)","url":"http:\/\/elections.interieur.gouv.fr\/MN2014\/006\/C1006049.html"},"resultat":{"libelle":"R&eacute;sultats re&ccedil;us 1er tour","url":"http:\/\/elections.interieur.gouv.fr\/MN2014\/006\/006049.html"}},"23":{"nom":"Coursegoules","Listes":{"libelle":"Candidats (Scrutin majoritaire)","url":"http:\/\/elections.interieur.gouv.fr\/MN2014\/006\/C1006050.html"},"resultat":{"libelle":"R&eacute;sultats re&ccedil;us 1er tour","url":"http:\/\/elections.interieur.gouv.fr\/MN2014\/006\/006050.html"}},"24":{"nom":"Cu&eacute;bris","Listes":{"libelle":"Candidats (Scrutin majoritaire)","url":"http:\/\/elections.interieur.gouv.fr\/MN2014\/006\/C1006052.html"},"resultat":{"libelle":"R&eacute;sultats re&ccedil;us 1er tour","url":"http:\/\/elections.interieur.gouv.fr\/MN2014\/006\/006052.html"}}}},"4":{"url":"http:\/\/elections.interieur.gouv.fr\/MN2014\/006\/006D.html","libelle":"D","villes":{"1":{"nom":"Daluis","Listes":{"libelle":"Candidats (Scrutin majoritaire)","url":"http:\/\/elections.interieur.gouv.fr\/MN2014\/006\/C1006053.html"},"resultat":{"libelle":"R&eacute;sultats re&ccedil;us 1er tour","url":"http:\/\/elections.interieur.gouv.fr\/MN2014\/006\/006053.html"}},"2":{"nom":"Drap","Listes":{"libelle":"Listes","url":"http:\/\/elections.interieur.gouv.fr\/MN2014\/006\/C1006054.html"},"resultat":{"libelle":"R&eacute;sultats re&ccedil;us 1er tour","url":"http:\/\/elections.interieur.gouv.fr\/MN2014\/006\/006054.html"}},"3":{"nom":"Duranus","Listes":{"libelle":"Candidats (Scrutin majoritaire)","url":"http:\/\/elections.interieur.gouv.fr\/MN2014\/006\/C1006055.html"},"resultat":{"libelle":"R&eacute;sultats re&ccedil;us 1er tour","url":"http:\/\/elections.interieur.gouv.fr\/MN2014\/006\/006055.html"}}}},"5":{"url":"http:\/\/elections.interieur.gouv.fr\/MN2014\/006\/006E.html","libelle":"E","villes":{"1":{"nom":"Entraunes","Listes":{"libelle":"Candidats (Scrutin majoritaire)","url":"http:\/\/elections.interieur.gouv.fr\/MN2014\/006\/C1006056.html"},"resultat":{"libelle":"R&eacute;sultats re&ccedil;us 1er tour","url":"http:\/\/elections.interieur.gouv.fr\/MN2014\/006\/006056.html"}},"2":{"nom":"Escragnolles","Listes":{"libelle":"Candidats (Scrutin majoritaire)","url":"http:\/\/elections.interieur.gouv.fr\/MN2014\/006\/C1006058.html"},"resultat":{"libelle":"R&eacute;sultats re&ccedil;us 1er tour","url":"http:\/\/elections.interieur.gouv.fr\/MN2014\/006\/006058.html"}},"3":{"nom":"Eze","Listes":{"libelle":"Listes","url":"http:\/\/elections.interieur.gouv.fr\/MN2014\/006\/C1006059.html"},"resultat":{"libelle":"R&eacute;sultats re&ccedil;us 1er tour","url":"http:\/\/elections.interieur.gouv.fr\/MN2014\/006\/006059.html"}}}},"6":{"url":"http:\/\/elections.interieur.gouv.fr\/MN2014\/006\/006F.html","libelle":"F","villes":{"1":{"nom":"Falicon","Listes":{"libelle":"Listes","url":"http:\/\/elections.interieur.gouv.fr\/MN2014\/006\/C1006060.html"},"resultat":{"libelle":"R&eacute;sultats re&ccedil;us 1er tour","url":"http:\/\/elections.interieur.gouv.fr\/MN2014\/006\/006060.html"}},"2":{"nom":"Fontan","Listes":{"libelle":"Candidats (Scrutin majoritaire)","url":"http:\/\/elections.interieur.gouv.fr\/MN2014\/006\/C1006062.html"},"resultat":{"libelle":"R&eacute;sultats re&ccedil;us 1er tour","url":"http:\/\/elections.interieur.gouv.fr\/MN2014\/006\/006062.html"}}}},"7":{"url":"http:\/\/elections.interieur.gouv.fr\/MN2014\/006\/006G.html","libelle":"G","villes":{"1":{"nom":"Gars","Listes":{"libelle":"Candidats (Scrutin majoritaire)","url":"http:\/\/elections.interieur.gouv.fr\/MN2014\/006\/C1006063.html"},"resultat":{"libelle":"R&eacute;sultats re&ccedil;us 1er tour","url":"http:\/\/elections.interieur.gouv.fr\/MN2014\/006\/006063.html"}},"2":{"nom":"Gatti&egrave;res","Listes":{"libelle":"Listes","url":"http:\/\/elections.interieur.gouv.fr\/MN2014\/006\/C1006064.html"},"resultat":{"libelle":"R&eacute;sultats re&ccedil;us 1er tour","url":"http:\/\/elections.interieur.gouv.fr\/MN2014\/006\/006064.html"}},"3":{"nom":"Gilette","Listes":{"libelle":"Listes","url":"http:\/\/elections.interieur.gouv.fr\/MN2014\/006\/C1006066.html"},"resultat":{"libelle":"R&eacute;sultats re&ccedil;us 1er tour","url":"http:\/\/elections.interieur.gouv.fr\/MN2014\/006\/006066.html"}},"4":{"nom":"Gorbio","Listes":{"libelle":"Listes","url":"http:\/\/elections.interieur.gouv.fr\/MN2014\/006\/C1006067.html"},"resultat":{"libelle":"R&eacute;sultats re&ccedil;us 1er tour","url":"http:\/\/elections.interieur.gouv.fr\/MN2014\/006\/006067.html"}},"5":{"nom":"Gourdon","Listes":{"libelle":"Candidats (Scrutin majoritaire)","url":"http:\/\/elections.interieur.gouv.fr\/MN2014\/006\/C1006068.html"},"resultat":{"libelle":"R&eacute;sultats re&ccedil;us 1er tour","url":"http:\/\/elections.interieur.gouv.fr\/MN2014\/006\/006068.html"}},"6":{"nom":"Grasse","Listes":{"libelle":"Listes","url":"http:\/\/elections.interieur.gouv.fr\/MN2014\/006\/C1006069.html"},"resultat":{"libelle":"R&eacute;sultats re&ccedil;us 1er tour","url":"http:\/\/elections.interieur.gouv.fr\/MN2014\/006\/006069.html"}},"7":{"nom":"Gr&eacute;oli&egrave;res","Listes":{"libelle":"Candidats (Scrutin majoritaire)","url":"http:\/\/elections.interieur.gouv.fr\/MN2014\/006\/C1006070.html"},"resultat":{"libelle":"R&eacute;sultats re&ccedil;us 1er tour","url":"http:\/\/elections.interieur.gouv.fr\/MN2014\/006\/006070.html"}},"8":{"nom":"Guillaumes","Listes":{"libelle":"Candidats (Scrutin majoritaire)","url":"http:\/\/elections.interieur.gouv.fr\/MN2014\/006\/C1006071.html"},"resultat":{"libelle":"R&eacute;sultats re&ccedil;us 1er tour","url":"http:\/\/elections.interieur.gouv.fr\/MN2014\/006\/006071.html"}}}},"8":{"url":"http:\/\/elections.interieur.gouv.fr\/MN2014\/006\/006I.html","libelle":"I","villes":{"1":{"nom":"Ilonse","Listes":{"libelle":"Candidats (Scrutin majoritaire)","url":"http:\/\/elections.interieur.gouv.fr\/MN2014\/006\/C1006072.html"},"resultat":{"libelle":"R&eacute;sultats re&ccedil;us 1er tour","url":"http:\/\/elections.interieur.gouv.fr\/MN2014\/006\/006072.html"}},"2":{"nom":"Isola","Listes":{"libelle":"Candidats (Scrutin majoritaire)","url":"http:\/\/elections.interieur.gouv.fr\/MN2014\/006\/C1006073.html"},"resultat":{"libelle":"R&eacute;sultats re&ccedil;us 1er tour","url":"http:\/\/elections.interieur.gouv.fr\/MN2014\/006\/006073.html"}}}},"9":{"url":"http:\/\/elections.interieur.gouv.fr\/MN2014\/006\/006L.html","libelle":"L","villes":{"1":{"nom":"La Boll&egrave;ne-V&eacute;subie","Listes":{"libelle":"Candidats (Scrutin majoritaire)","url":"http:\/\/elections.interieur.gouv.fr\/MN2014\/006\/C1006020.html"},"resultat":{"libelle":"R&eacute;sultats re&ccedil;us 1er tour","url":"http:\/\/elections.interieur.gouv.fr\/MN2014\/006\/006020.html"}},"2":{"nom":"La Brigue","Listes":{"libelle":"Candidats (Scrutin majoritaire)","url":"http:\/\/elections.interieur.gouv.fr\/MN2014\/006\/C1006162.html"},"resultat":{"libelle":"R&eacute;sultats re&ccedil;us 1er tour","url":"http:\/\/elections.interieur.gouv.fr\/MN2014\/006\/006162.html"}},"3":{"nom":"La Colle-Sur-Loup","Listes":{"libelle":"Listes","url":"http:\/\/elections.interieur.gouv.fr\/MN2014\/006\/C1006044.html"},"resultat":{"libelle":"R&eacute;sultats re&ccedil;us 1er tour","url":"http:\/\/elections.interieur.gouv.fr\/MN2014\/006\/006044.html"}},"4":{"nom":"La Croix-Sur-Roudoule","Listes":{"libelle":"Candidats (Scrutin majoritaire)","url":"http:\/\/elections.interieur.gouv.fr\/MN2014\/006\/C1006051.html"},"resultat":{"libelle":"R&eacute;sultats re&ccedil;us 1er tour","url":"http:\/\/elections.interieur.gouv.fr\/MN2014\/006\/006051.html"}},"5":{"nom":"La Gaude","Listes":{"libelle":"Listes","url":"http:\/\/elections.interieur.gouv.fr\/MN2014\/006\/C1006065.html"},"resultat":{"libelle":"R&eacute;sultats re&ccedil;us 1er tour","url":"http:\/\/elections.interieur.gouv.fr\/MN2014\/006\/006065.html"}},"6":{"nom":"La Penne","Listes":{"libelle":"Candidats (Scrutin majoritaire)","url":"http:\/\/elections.interieur.gouv.fr\/MN2014\/006\/C1006093.html"},"resultat":{"libelle":"R&eacute;sultats re&ccedil;us 1er tour","url":"http:\/\/elections.interieur.gouv.fr\/MN2014\/006\/006093.html"}},"7":{"nom":"La Roquette-Sur-Siagne","Listes":{"libelle":"Listes","url":"http:\/\/elections.interieur.gouv.fr\/MN2014\/006\/C1006108.html"},"resultat":{"libelle":"R&eacute;sultats re&ccedil;us 1er tour","url":"http:\/\/elections.interieur.gouv.fr\/MN2014\/006\/006108.html"}},"8":{"nom":"La Roquette-Sur-Var","Listes":{"libelle":"Candidats (Scrutin majoritaire)","url":"http:\/\/elections.interieur.gouv.fr\/MN2014\/006\/C1006109.html"},"resultat":{"libelle":"R&eacute;sultats re&ccedil;us 1er tour","url":"http:\/\/elections.interieur.gouv.fr\/MN2014\/006\/006109.html"}},"9":{"nom":"La Tour","Listes":{"libelle":"Candidats (Scrutin majoritaire)","url":"http:\/\/elections.interieur.gouv.fr\/MN2014\/006\/C1006144.html"},"resultat":{"libelle":"R&eacute;sultats re&ccedil;us 1er tour","url":"http:\/\/elections.interieur.gouv.fr\/MN2014\/006\/006144.html"}},"10":{"nom":"La Trinit&eacute;","Listes":{"libelle":"Listes","url":"http:\/\/elections.interieur.gouv.fr\/MN2014\/006\/C1006149.html"},"resultat":{"libelle":"R&eacute;sultats re&ccedil;us 1er tour","url":"http:\/\/elections.interieur.gouv.fr\/MN2014\/006\/006149.html"}},"11":{"nom":"La Turbie","Listes":{"libelle":"Listes","url":"http:\/\/elections.interieur.gouv.fr\/MN2014\/006\/C1006150.html"},"resultat":{"libelle":"R&eacute;sultats re&ccedil;us 1er tour","url":"http:\/\/elections.interieur.gouv.fr\/MN2014\/006\/006150.html"}},"12":{"nom":"Lantosque","Listes":{"libelle":"Listes","url":"http:\/\/elections.interieur.gouv.fr\/MN2014\/006\/C1006074.html"},"resultat":{"libelle":"R&eacute;sultats re&ccedil;us 1er tour","url":"http:\/\/elections.interieur.gouv.fr\/MN2014\/006\/006074.html"}},"13":{"nom":"Le Bar-Sur-Loup","Listes":{"libelle":"Listes","url":"http:\/\/elections.interieur.gouv.fr\/MN2014\/006\/C1006010.html"},"resultat":{"libelle":"R&eacute;sultats re&ccedil;us 1er tour","url":"http:\/\/elections.interieur.gouv.fr\/MN2014\/006\/006010.html"}},"14":{"nom":"Le Broc","Listes":{"libelle":"Listes","url":"http:\/\/elections.interieur.gouv.fr\/MN2014\/006\/C1006025.html"},"resultat":{"libelle":"R&eacute;sultats re&ccedil;us 1er tour","url":"http:\/\/elections.interieur.gouv.fr\/MN2014\/006\/006025.html"}},"15":{"nom":"Le Cannet","Listes":{"libelle":"Listes","url":"http:\/\/elections.interieur.gouv.fr\/MN2014\/006\/C1006030.html"},"resultat":{"libelle":"R&eacute;sultats re&ccedil;us 1er tour","url":"http:\/\/elections.interieur.gouv.fr\/MN2014\/006\/006030.html"}},"16":{"nom":"Le Mas","Listes":{"libelle":"Candidats (Scrutin majoritaire)","url":"http:\/\/elections.interieur.gouv.fr\/MN2014\/006\/C1006081.html"},"resultat":{"libelle":"R&eacute;sultats re&ccedil;us 1er tour","url":"http:\/\/elections.interieur.gouv.fr\/MN2014\/006\/006081.html"}},"17":{"nom":"Le Rouret","Listes":{"libelle":"Listes","url":"http:\/\/elections.interieur.gouv.fr\/MN2014\/006\/C1006112.html"},"resultat":{"libelle":"R&eacute;sultats re&ccedil;us 1er tour","url":"http:\/\/elections.interieur.gouv.fr\/MN2014\/006\/006112.html"}},"18":{"nom":"Le Tignet","Listes":{"libelle":"Listes","url":"http:\/\/elections.interieur.gouv.fr\/MN2014\/006\/C1006140.html"},"resultat":{"libelle":"R&eacute;sultats re&ccedil;us 1er tour","url":"http:\/\/elections.interieur.gouv.fr\/MN2014\/006\/006140.html"}},"19":{"nom":"Les Ferres","Listes":{"libelle":"Candidats (Scrutin majoritaire)","url":"http:\/\/elections.interieur.gouv.fr\/MN2014\/006\/C1006061.html"},"resultat":{"libelle":"R&eacute;sultats re&ccedil;us 1er tour","url":"http:\/\/elections.interieur.gouv.fr\/MN2014\/006\/006061.html"}},"20":{"nom":"Les Mujouls","Listes":{"libelle":"Candidats (Scrutin majoritaire)","url":"http:\/\/elections.interieur.gouv.fr\/MN2014\/006\/C1006087.html"},"resultat":{"libelle":"R&eacute;sultats re&ccedil;us 1er tour","url":"http:\/\/elections.interieur.gouv.fr\/MN2014\/006\/006087.html"}},"21":{"nom":"L'Escar&egrave;ne","Listes":{"libelle":"Listes","url":"http:\/\/elections.interieur.gouv.fr\/MN2014\/006\/C1006057.html"},"resultat":{"libelle":"R&eacute;sultats re&ccedil;us 1er tour","url":"http:\/\/elections.interieur.gouv.fr\/MN2014\/006\/006057.html"}},"22":{"nom":"Levens","Listes":{"libelle":"Listes","url":"http:\/\/elections.interieur.gouv.fr\/MN2014\/006\/C1006075.html"},"resultat":{"libelle":"R&eacute;sultats re&ccedil;us 1er tour","url":"http:\/\/elections.interieur.gouv.fr\/MN2014\/006\/006075.html"}},"23":{"nom":"Lieuche","Listes":{"libelle":"Candidats (Scrutin majoritaire)","url":"http:\/\/elections.interieur.gouv.fr\/MN2014\/006\/C1006076.html"},"resultat":{"libelle":"R&eacute;sultats re&ccedil;us 1er tour","url":"http:\/\/elections.interieur.gouv.fr\/MN2014\/006\/006076.html"}},"24":{"nom":"Luc&eacute;ram","Listes":{"libelle":"Listes","url":"http:\/\/elections.interieur.gouv.fr\/MN2014\/006\/C1006077.html"},"resultat":{"libelle":"R&eacute;sultats re&ccedil;us 1er tour","url":"http:\/\/elections.interieur.gouv.fr\/MN2014\/006\/006077.html"}}}},"10":{"url":"http:\/\/elections.interieur.gouv.fr\/MN2014\/006\/006M.html","libelle":"M","villes":{"1":{"nom":"Malauss&egrave;ne","Listes":{"libelle":"Candidats (Scrutin majoritaire)","url":"http:\/\/elections.interieur.gouv.fr\/MN2014\/006\/C1006078.html"},"resultat":{"libelle":"R&eacute;sultats re&ccedil;us 1er tour","url":"http:\/\/elections.interieur.gouv.fr\/MN2014\/006\/006078.html"}},"2":{"nom":"Mandelieu-La-Napoule","Listes":{"libelle":"Listes","url":"http:\/\/elections.interieur.gouv.fr\/MN2014\/006\/C1006079.html"},"resultat":{"libelle":"R&eacute;sultats re&ccedil;us 1er tour","url":"http:\/\/elections.interieur.gouv.fr\/MN2014\/006\/006079.html"}},"3":{"nom":"Marie","Listes":{"libelle":"Candidats (Scrutin majoritaire)","url":"http:\/\/elections.interieur.gouv.fr\/MN2014\/006\/C1006080.html"},"resultat":{"libelle":"R&eacute;sultats re&ccedil;us 1er tour","url":"http:\/\/elections.interieur.gouv.fr\/MN2014\/006\/006080.html"}},"4":{"nom":"Massoins","Listes":{"libelle":"Candidats (Scrutin majoritaire)","url":"http:\/\/elections.interieur.gouv.fr\/MN2014\/006\/C1006082.html"},"resultat":{"libelle":"R&eacute;sultats re&ccedil;us 1er tour","url":"http:\/\/elections.interieur.gouv.fr\/MN2014\/006\/006082.html"}},"5":{"nom":"Menton","Listes":{"libelle":"Listes","url":"http:\/\/elections.interieur.gouv.fr\/MN2014\/006\/C1006083.html"},"resultat":{"libelle":"R&eacute;sultats re&ccedil;us 1er tour","url":"http:\/\/elections.interieur.gouv.fr\/MN2014\/006\/006083.html"}},"6":{"nom":"Mouans-Sartoux","Listes":{"libelle":"Listes","url":"http:\/\/elections.interieur.gouv.fr\/MN2014\/006\/C1006084.html"},"resultat":{"libelle":"R&eacute;sultats re&ccedil;us 1er tour","url":"http:\/\/elections.interieur.gouv.fr\/MN2014\/006\/006084.html"}},"7":{"nom":"Mougins","Listes":{"libelle":"Listes","url":"http:\/\/elections.interieur.gouv.fr\/MN2014\/006\/C1006085.html"},"resultat":{"libelle":"R&eacute;sultats re&ccedil;us 1er tour","url":"http:\/\/elections.interieur.gouv.fr\/MN2014\/006\/006085.html"}},"8":{"nom":"Moulinet","Listes":{"libelle":"Candidats (Scrutin majoritaire)","url":"http:\/\/elections.interieur.gouv.fr\/MN2014\/006\/C1006086.html"},"resultat":{"libelle":"R&eacute;sultats re&ccedil;us 1er tour","url":"http:\/\/elections.interieur.gouv.fr\/MN2014\/006\/006086.html"}}}},"11":{"url":"http:\/\/elections.interieur.gouv.fr\/MN2014\/006\/006N.html","libelle":"N","villes":{"1":{"nom":"Nice","Listes":{"libelle":"Listes","url":"http:\/\/elections.interieur.gouv.fr\/MN2014\/006\/C1006088.html"},"resultat":{"libelle":"R&eacute;sultats re&ccedil;us 1er tour","url":"http:\/\/elections.interieur.gouv.fr\/MN2014\/006\/006088.html"}}}},"12":{"url":"http:\/\/elections.interieur.gouv.fr\/MN2014\/006\/006O.html","libelle":"O","villes":{"1":{"nom":"Opio","Listes":{"libelle":"Listes","url":"http:\/\/elections.interieur.gouv.fr\/MN2014\/006\/C1006089.html"},"resultat":{"libelle":"R&eacute;sultats re&ccedil;us 1er tour","url":"http:\/\/elections.interieur.gouv.fr\/MN2014\/006\/006089.html"}}}},"13":{"url":"http:\/\/elections.interieur.gouv.fr\/MN2014\/006\/006P.html","libelle":"P","villes":{"1":{"nom":"P&eacute;gomas","Listes":{"libelle":"Listes","url":"http:\/\/elections.interieur.gouv.fr\/MN2014\/006\/C1006090.html"},"resultat":{"libelle":"R&eacute;sultats re&ccedil;us 1er tour","url":"http:\/\/elections.interieur.gouv.fr\/MN2014\/006\/006090.html"}},"2":{"nom":"Peille","Listes":{"libelle":"Listes","url":"http:\/\/elections.interieur.gouv.fr\/MN2014\/006\/C1006091.html"},"resultat":{"libelle":"R&eacute;sultats re&ccedil;us 1er tour","url":"http:\/\/elections.interieur.gouv.fr\/MN2014\/006\/006091.html"}},"3":{"nom":"Peillon","Listes":{"libelle":"Listes","url":"http:\/\/elections.interieur.gouv.fr\/MN2014\/006\/C1006092.html"},"resultat":{"libelle":"R&eacute;sultats re&ccedil;us 1er tour","url":"http:\/\/elections.interieur.gouv.fr\/MN2014\/006\/006092.html"}},"4":{"nom":"P&eacute;one","Listes":{"libelle":"Candidats (Scrutin majoritaire)","url":"http:\/\/elections.interieur.gouv.fr\/MN2014\/006\/C1006094.html"},"resultat":{"libelle":"R&eacute;sultats re&ccedil;us 1er tour","url":"http:\/\/elections.interieur.gouv.fr\/MN2014\/006\/006094.html"}},"5":{"nom":"Peymeinade","Listes":{"libelle":"Listes","url":"http:\/\/elections.interieur.gouv.fr\/MN2014\/006\/C1006095.html"},"resultat":{"libelle":"R&eacute;sultats re&ccedil;us 1er tour","url":"http:\/\/elections.interieur.gouv.fr\/MN2014\/006\/006095.html"}},"6":{"nom":"Pierlas","Listes":{"libelle":"Candidats (Scrutin majoritaire)","url":"http:\/\/elections.interieur.gouv.fr\/MN2014\/006\/C1006096.html"},"resultat":{"libelle":"R&eacute;sultats re&ccedil;us 1er tour","url":"http:\/\/elections.interieur.gouv.fr\/MN2014\/006\/006096.html"}},"7":{"nom":"Pierrefeu","Listes":{"libelle":"Candidats (Scrutin majoritaire)","url":"http:\/\/elections.interieur.gouv.fr\/MN2014\/006\/C1006097.html"},"resultat":{"libelle":"R&eacute;sultats re&ccedil;us 1er tour","url":"http:\/\/elections.interieur.gouv.fr\/MN2014\/006\/006097.html"}},"8":{"nom":"Puget-Rostang","Listes":{"libelle":"Candidats (Scrutin majoritaire)","url":"http:\/\/elections.interieur.gouv.fr\/MN2014\/006\/C1006098.html"},"resultat":{"libelle":"R&eacute;sultats re&ccedil;us 1er tour","url":"http:\/\/elections.interieur.gouv.fr\/MN2014\/006\/006098.html"}},"9":{"nom":"Puget-Th&eacute;niers","Listes":{"libelle":"Listes","url":"http:\/\/elections.interieur.gouv.fr\/MN2014\/006\/C1006099.html"},"resultat":{"libelle":"R&eacute;sultats re&ccedil;us 1er tour","url":"http:\/\/elections.interieur.gouv.fr\/MN2014\/006\/006099.html"}}}},"14":{"url":"http:\/\/elections.interieur.gouv.fr\/MN2014\/006\/006R.html","libelle":"R","villes":{"1":{"nom":"Revest-Les-Roches","Listes":{"libelle":"Candidats (Scrutin majoritaire)","url":"http:\/\/elections.interieur.gouv.fr\/MN2014\/006\/C1006100.html"},"resultat":{"libelle":"R&eacute;sultats re&ccedil;us 1er tour","url":"http:\/\/elections.interieur.gouv.fr\/MN2014\/006\/006100.html"}},"2":{"nom":"Rigaud","Listes":{"libelle":"Candidats (Scrutin majoritaire)","url":"http:\/\/elections.interieur.gouv.fr\/MN2014\/006\/C1006101.html"},"resultat":{"libelle":"R&eacute;sultats re&ccedil;us 1er tour","url":"http:\/\/elections.interieur.gouv.fr\/MN2014\/006\/006101.html"}},"3":{"nom":"Rimplas","Listes":{"libelle":"Candidats (Scrutin majoritaire)","url":"http:\/\/elections.interieur.gouv.fr\/MN2014\/006\/C1006102.html"},"resultat":{"libelle":"R&eacute;sultats re&ccedil;us 1er tour","url":"http:\/\/elections.interieur.gouv.fr\/MN2014\/006\/006102.html"}},"4":{"nom":"Roquebilli&egrave;re","Listes":{"libelle":"Listes","url":"http:\/\/elections.interieur.gouv.fr\/MN2014\/006\/C1006103.html"},"resultat":{"libelle":"R&eacute;sultats re&ccedil;us 1er tour","url":"http:\/\/elections.interieur.gouv.fr\/MN2014\/006\/006103.html"}},"5":{"nom":"Roquebrune-Cap-Martin","Listes":{"libelle":"Listes","url":"http:\/\/elections.interieur.gouv.fr\/MN2014\/006\/C1006104.html"},"resultat":{"libelle":"R&eacute;sultats re&ccedil;us 1er tour","url":"http:\/\/elections.interieur.gouv.fr\/MN2014\/006\/006104.html"}},"6":{"nom":"Roquefort-Les-Pins","Listes":{"libelle":"Listes","url":"http:\/\/elections.interieur.gouv.fr\/MN2014\/006\/C1006105.html"},"resultat":{"libelle":"R&eacute;sultats re&ccedil;us 1er tour","url":"http:\/\/elections.interieur.gouv.fr\/MN2014\/006\/006105.html"}},"7":{"nom":"Roquesteron","Listes":{"libelle":"Candidats (Scrutin majoritaire)","url":"http:\/\/elections.interieur.gouv.fr\/MN2014\/006\/C1006106.html"},"resultat":{"libelle":"R&eacute;sultats re&ccedil;us 1er tour","url":"http:\/\/elections.interieur.gouv.fr\/MN2014\/006\/006106.html"}},"8":{"nom":"Roquest&eacute;ron-Grasse","Listes":{"libelle":"Candidats (Scrutin majoritaire)","url":"http:\/\/elections.interieur.gouv.fr\/MN2014\/006\/C1006107.html"},"resultat":{"libelle":"R&eacute;sultats re&ccedil;us 1er tour","url":"http:\/\/elections.interieur.gouv.fr\/MN2014\/006\/006107.html"}},"9":{"nom":"Roubion","Listes":{"libelle":"Candidats (Scrutin majoritaire)","url":"http:\/\/elections.interieur.gouv.fr\/MN2014\/006\/C1006110.html"},"resultat":{"libelle":"R&eacute;sultats re&ccedil;us 1er tour","url":"http:\/\/elections.interieur.gouv.fr\/MN2014\/006\/006110.html"}},"10":{"nom":"Roure","Listes":{"libelle":"Candidats (Scrutin majoritaire)","url":"http:\/\/elections.interieur.gouv.fr\/MN2014\/006\/C1006111.html"},"resultat":{"libelle":"R&eacute;sultats re&ccedil;us 1er tour","url":"http:\/\/elections.interieur.gouv.fr\/MN2014\/006\/006111.html"}}}},"15":{"url":"http:\/\/elections.interieur.gouv.fr\/MN2014\/006\/006S.html","libelle":"S","villes":{"1":{"nom":"Saint-Andr&eacute; De La Roche","Listes":{"libelle":"Listes","url":"http:\/\/elections.interieur.gouv.fr\/MN2014\/006\/C1006114.html"},"resultat":{"libelle":"R&eacute;sultats re&ccedil;us 1er tour","url":"http:\/\/elections.interieur.gouv.fr\/MN2014\/006\/006114.html"}},"2":{"nom":"Saint-Antonin","Listes":{"libelle":"Candidats (Scrutin majoritaire)","url":"http:\/\/elections.interieur.gouv.fr\/MN2014\/006\/C1006115.html"},"resultat":{"libelle":"R&eacute;sultats re&ccedil;us 1er tour","url":"http:\/\/elections.interieur.gouv.fr\/MN2014\/006\/006115.html"}},"3":{"nom":"Saint-Auban","Listes":{"libelle":"Candidats (Scrutin majoritaire)","url":"http:\/\/elections.interieur.gouv.fr\/MN2014\/006\/C1006116.html"},"resultat":{"libelle":"R&eacute;sultats re&ccedil;us 1er tour","url":"http:\/\/elections.interieur.gouv.fr\/MN2014\/006\/006116.html"}},"4":{"nom":"Saint-Blaise","Listes":{"libelle":"Candidats (Scrutin majoritaire)","url":"http:\/\/elections.interieur.gouv.fr\/MN2014\/006\/C1006117.html"},"resultat":{"libelle":"R&eacute;sultats re&ccedil;us 1er tour","url":"http:\/\/elections.interieur.gouv.fr\/MN2014\/006\/006117.html"}},"5":{"nom":"Saint-C&eacute;zaire-Sur-Siagne","Listes":{"libelle":"Listes","url":"http:\/\/elections.interieur.gouv.fr\/MN2014\/006\/C1006118.html"},"resultat":{"libelle":"R&eacute;sultats re&ccedil;us 1er tour","url":"http:\/\/elections.interieur.gouv.fr\/MN2014\/006\/006118.html"}},"6":{"nom":"Saint-Dalmas-Le-Selvage","Listes":{"libelle":"Candidats (Scrutin majoritaire)","url":"http:\/\/elections.interieur.gouv.fr\/MN2014\/006\/C1006119.html"},"resultat":{"libelle":"R&eacute;sultats re&ccedil;us 1er tour","url":"http:\/\/elections.interieur.gouv.fr\/MN2014\/006\/006119.html"}},"7":{"nom":"Sainte-Agn&egrave;s","Listes":{"libelle":"Listes","url":"http:\/\/elections.interieur.gouv.fr\/MN2014\/006\/C1006113.html"},"resultat":{"libelle":"R&eacute;sultats re&ccedil;us 1er tour","url":"http:\/\/elections.interieur.gouv.fr\/MN2014\/006\/006113.html"}},"8":{"nom":"Saint-Etienne-De-Tin&eacute;e","Listes":{"libelle":"Listes","url":"http:\/\/elections.interieur.gouv.fr\/MN2014\/006\/C1006120.html"},"resultat":{"libelle":"R&eacute;sultats re&ccedil;us 1er tour","url":"http:\/\/elections.interieur.gouv.fr\/MN2014\/006\/006120.html"}},"9":{"nom":"Saint-Jean-Cap-Ferrat","Listes":{"libelle":"Listes","url":"http:\/\/elections.interieur.gouv.fr\/MN2014\/006\/C1006121.html"},"resultat":{"libelle":"R&eacute;sultats re&ccedil;us 1er tour","url":"http:\/\/elections.interieur.gouv.fr\/MN2014\/006\/006121.html"}},"10":{"nom":"Saint-Jeannet","Listes":{"libelle":"Listes","url":"http:\/\/elections.interieur.gouv.fr\/MN2014\/006\/C1006122.html"},"resultat":{"libelle":"R&eacute;sultats re&ccedil;us 1er tour","url":"http:\/\/elections.interieur.gouv.fr\/MN2014\/006\/006122.html"}},"11":{"nom":"Saint-Laurent-Du-Var","Listes":{"libelle":"Listes","url":"http:\/\/elections.interieur.gouv.fr\/MN2014\/006\/C1006123.html"},"resultat":{"libelle":"R&eacute;sultats re&ccedil;us 1er tour","url":"http:\/\/elections.interieur.gouv.fr\/MN2014\/006\/006123.html"}},"12":{"nom":"Saint-L&eacute;ger","Listes":{"libelle":"Candidats (Scrutin majoritaire)","url":"http:\/\/elections.interieur.gouv.fr\/MN2014\/006\/C1006124.html"},"resultat":{"libelle":"R&eacute;sultats re&ccedil;us 1er tour","url":"http:\/\/elections.interieur.gouv.fr\/MN2014\/006\/006124.html"}},"13":{"nom":"Saint-Martin-D'Entraunes","Listes":{"libelle":"Candidats (Scrutin majoritaire)","url":"http:\/\/elections.interieur.gouv.fr\/MN2014\/006\/C1006125.html"},"resultat":{"libelle":"R&eacute;sultats re&ccedil;us 1er tour","url":"http:\/\/elections.interieur.gouv.fr\/MN2014\/006\/006125.html"}},"14":{"nom":"Saint-Martin-Du-Var","Listes":{"libelle":"Listes","url":"http:\/\/elections.interieur.gouv.fr\/MN2014\/006\/C1006126.html"},"resultat":{"libelle":"R&eacute;sultats re&ccedil;us 1er tour","url":"http:\/\/elections.interieur.gouv.fr\/MN2014\/006\/006126.html"}},"15":{"nom":"Saint-Martin-V&eacute;subie","Listes":{"libelle":"Listes","url":"http:\/\/elections.interieur.gouv.fr\/MN2014\/006\/C1006127.html"},"resultat":{"libelle":"R&eacute;sultats re&ccedil;us 1er tour","url":"http:\/\/elections.interieur.gouv.fr\/MN2014\/006\/006127.html"}},"16":{"nom":"Saint-Paul","Listes":{"libelle":"Listes","url":"http:\/\/elections.interieur.gouv.fr\/MN2014\/006\/C1006128.html"},"resultat":{"libelle":"R&eacute;sultats re&ccedil;us 1er tour","url":"http:\/\/elections.interieur.gouv.fr\/MN2014\/006\/006128.html"}},"17":{"nom":"Saint-Sauveur-Sur-Tin&eacute;e","Listes":{"libelle":"Candidats (Scrutin majoritaire)","url":"http:\/\/elections.interieur.gouv.fr\/MN2014\/006\/C1006129.html"},"resultat":{"libelle":"R&eacute;sultats re&ccedil;us 1er tour","url":"http:\/\/elections.interieur.gouv.fr\/MN2014\/006\/006129.html"}},"18":{"nom":"Saint-Vallier-De-Thiey","Listes":{"libelle":"Listes","url":"http:\/\/elections.interieur.gouv.fr\/MN2014\/006\/C1006130.html"},"resultat":{"libelle":"R&eacute;sultats re&ccedil;us 1er tour","url":"http:\/\/elections.interieur.gouv.fr\/MN2014\/006\/006130.html"}},"19":{"nom":"Sallagriffon","Listes":{"libelle":"Candidats (Scrutin majoritaire)","url":"http:\/\/elections.interieur.gouv.fr\/MN2014\/006\/C1006131.html"},"resultat":{"libelle":"R&eacute;sultats re&ccedil;us 1er tour","url":"http:\/\/elections.interieur.gouv.fr\/MN2014\/006\/006131.html"}},"20":{"nom":"Saorge","Listes":{"libelle":"Candidats (Scrutin majoritaire)","url":"http:\/\/elections.interieur.gouv.fr\/MN2014\/006\/C1006132.html"},"resultat":{"libelle":"R&eacute;sultats re&ccedil;us 1er tour","url":"http:\/\/elections.interieur.gouv.fr\/MN2014\/006\/006132.html"}},"21":{"nom":"Sauze","Listes":{"libelle":"Candidats (Scrutin majoritaire)","url":"http:\/\/elections.interieur.gouv.fr\/MN2014\/006\/C1006133.html"},"resultat":{"libelle":"R&eacute;sultats re&ccedil;us 1er tour","url":"http:\/\/elections.interieur.gouv.fr\/MN2014\/006\/006133.html"}},"22":{"nom":"S&eacute;ranon","Listes":{"libelle":"Candidats (Scrutin majoritaire)","url":"http:\/\/elections.interieur.gouv.fr\/MN2014\/006\/C1006134.html"},"resultat":{"libelle":"R&eacute;sultats re&ccedil;us 1er tour","url":"http:\/\/elections.interieur.gouv.fr\/MN2014\/006\/006134.html"}},"23":{"nom":"Sigale","Listes":{"libelle":"Candidats (Scrutin majoritaire)","url":"http:\/\/elections.interieur.gouv.fr\/MN2014\/006\/C1006135.html"},"resultat":{"libelle":"R&eacute;sultats re&ccedil;us 1er tour","url":"http:\/\/elections.interieur.gouv.fr\/MN2014\/006\/006135.html"}},"24":{"nom":"Sospel","Listes":{"libelle":"Listes","url":"http:\/\/elections.interieur.gouv.fr\/MN2014\/006\/C1006136.html"},"resultat":{"libelle":"R&eacute;sultats re&ccedil;us 1er tour","url":"http:\/\/elections.interieur.gouv.fr\/MN2014\/006\/006136.html"}},"25":{"nom":"Sp&eacute;rac&egrave;des","Listes":{"libelle":"Listes","url":"http:\/\/elections.interieur.gouv.fr\/MN2014\/006\/C1006137.html"},"resultat":{"libelle":"R&eacute;sultats re&ccedil;us 1er tour","url":"http:\/\/elections.interieur.gouv.fr\/MN2014\/006\/006137.html"}}}},"16":{"url":"http:\/\/elections.interieur.gouv.fr\/MN2014\/006\/006T.html","libelle":"T","villes":{"1":{"nom":"Tende","Listes":{"libelle":"Listes","url":"http:\/\/elections.interieur.gouv.fr\/MN2014\/006\/C1006163.html"},"resultat":{"libelle":"R&eacute;sultats re&ccedil;us 1er tour","url":"http:\/\/elections.interieur.gouv.fr\/MN2014\/006\/006163.html"}},"2":{"nom":"Th&eacute;oule-Sur-Mer","Listes":{"libelle":"Listes","url":"http:\/\/elections.interieur.gouv.fr\/MN2014\/006\/C1006138.html"},"resultat":{"libelle":"R&eacute;sultats re&ccedil;us 1er tour","url":"http:\/\/elections.interieur.gouv.fr\/MN2014\/006\/006138.html"}},"3":{"nom":"Thi&eacute;ry","Listes":{"libelle":"Candidats (Scrutin majoritaire)","url":"http:\/\/elections.interieur.gouv.fr\/MN2014\/006\/C1006139.html"},"resultat":{"libelle":"R&eacute;sultats re&ccedil;us 1er tour","url":"http:\/\/elections.interieur.gouv.fr\/MN2014\/006\/006139.html"}},"4":{"nom":"Toudon","Listes":{"libelle":"Candidats (Scrutin majoritaire)","url":"http:\/\/elections.interieur.gouv.fr\/MN2014\/006\/C1006141.html"},"resultat":{"libelle":"R&eacute;sultats re&ccedil;us 1er tour","url":"http:\/\/elections.interieur.gouv.fr\/MN2014\/006\/006141.html"}},"5":{"nom":"Tou&euml;t-De-L'Escar&egrave;ne","Listes":{"libelle":"Candidats (Scrutin majoritaire)","url":"http:\/\/elections.interieur.gouv.fr\/MN2014\/006\/C1006142.html"},"resultat":{"libelle":"R&eacute;sultats re&ccedil;us 1er tour","url":"http:\/\/elections.interieur.gouv.fr\/MN2014\/006\/006142.html"}},"6":{"nom":"Tou&euml;t-Sur-Var","Listes":{"libelle":"Candidats (Scrutin majoritaire)","url":"http:\/\/elections.interieur.gouv.fr\/MN2014\/006\/C1006143.html"},"resultat":{"libelle":"R&eacute;sultats re&ccedil;us 1er tour","url":"http:\/\/elections.interieur.gouv.fr\/MN2014\/006\/006143.html"}},"7":{"nom":"Tourette-Du-Ch&acirc;teau","Listes":{"libelle":"Candidats (Scrutin majoritaire)","url":"http:\/\/elections.interieur.gouv.fr\/MN2014\/006\/C1006145.html"},"resultat":{"libelle":"R&eacute;sultats re&ccedil;us 1er tour","url":"http:\/\/elections.interieur.gouv.fr\/MN2014\/006\/006145.html"}},"8":{"nom":"Tournefort","Listes":{"libelle":"Candidats (Scrutin majoritaire)","url":"http:\/\/elections.interieur.gouv.fr\/MN2014\/006\/C1006146.html"},"resultat":{"libelle":"R&eacute;sultats re&ccedil;us 1er tour","url":"http:\/\/elections.interieur.gouv.fr\/MN2014\/006\/006146.html"}},"9":{"nom":"Tourrette-Levens","Listes":{"libelle":"Listes","url":"http:\/\/elections.interieur.gouv.fr\/MN2014\/006\/C1006147.html"},"resultat":{"libelle":"R&eacute;sultats re&ccedil;us 1er tour","url":"http:\/\/elections.interieur.gouv.fr\/MN2014\/006\/006147.html"}},"10":{"nom":"Tourrettes-Sur-Loup","Listes":{"libelle":"Listes","url":"http:\/\/elections.interieur.gouv.fr\/MN2014\/006\/C1006148.html"},"resultat":{"libelle":"R&eacute;sultats re&ccedil;us 1er tour","url":"http:\/\/elections.interieur.gouv.fr\/MN2014\/006\/006148.html"}}}},"17":{"url":"http:\/\/elections.interieur.gouv.fr\/MN2014\/006\/006U.html","libelle":"U","villes":{"1":{"nom":"Utelle","Listes":{"libelle":"Candidats (Scrutin majoritaire)","url":"http:\/\/elections.interieur.gouv.fr\/MN2014\/006\/C1006151.html"},"resultat":{"libelle":"R&eacute;sultats re&ccedil;us 1er tour","url":"http:\/\/elections.interieur.gouv.fr\/MN2014\/006\/006151.html"}}}},"18":{"url":"http:\/\/elections.interieur.gouv.fr\/MN2014\/006\/006V.html","libelle":"V","villes":{"1":{"nom":"Valbonne","Listes":{"libelle":"Listes","url":"http:\/\/elections.interieur.gouv.fr\/MN2014\/006\/C1006152.html"},"resultat":{"libelle":"R&eacute;sultats re&ccedil;us 1er tour","url":"http:\/\/elections.interieur.gouv.fr\/MN2014\/006\/006152.html"}},"2":{"nom":"Valdeblore","Listes":{"libelle":"Candidats (Scrutin majoritaire)","url":"http:\/\/elections.interieur.gouv.fr\/MN2014\/006\/C1006153.html"},"resultat":{"libelle":"R&eacute;sultats re&ccedil;us 1er tour","url":"http:\/\/elections.interieur.gouv.fr\/MN2014\/006\/006153.html"}},"3":{"nom":"Valderoure","Listes":{"libelle":"Candidats (Scrutin majoritaire)","url":"http:\/\/elections.interieur.gouv.fr\/MN2014\/006\/C1006154.html"},"resultat":{"libelle":"R&eacute;sultats re&ccedil;us 1er tour","url":"http:\/\/elections.interieur.gouv.fr\/MN2014\/006\/006154.html"}},"4":{"nom":"Vallauris","Listes":{"libelle":"Listes","url":"http:\/\/elections.interieur.gouv.fr\/MN2014\/006\/C1006155.html"},"resultat":{"libelle":"R&eacute;sultats re&ccedil;us 1er tour","url":"http:\/\/elections.interieur.gouv.fr\/MN2014\/006\/006155.html"}},"5":{"nom":"Venanson","Listes":{"libelle":"Candidats (Scrutin majoritaire)","url":"http:\/\/elections.interieur.gouv.fr\/MN2014\/006\/C1006156.html"},"resultat":{"libelle":"R&eacute;sultats re&ccedil;us 1er tour","url":"http:\/\/elections.interieur.gouv.fr\/MN2014\/006\/006156.html"}},"6":{"nom":"Vence","Listes":{"libelle":"Listes","url":"http:\/\/elections.interieur.gouv.fr\/MN2014\/006\/C1006157.html"},"resultat":{"libelle":"R&eacute;sultats re&ccedil;us 1er tour","url":"http:\/\/elections.interieur.gouv.fr\/MN2014\/006\/006157.html"}},"7":{"nom":"Villars-Sur-Var","Listes":{"libelle":"Candidats (Scrutin majoritaire)","url":"http:\/\/elections.interieur.gouv.fr\/MN2014\/006\/C1006158.html"},"resultat":{"libelle":"R&eacute;sultats re&ccedil;us 1er tour","url":"http:\/\/elections.interieur.gouv.fr\/MN2014\/006\/006158.html"}},"8":{"nom":"Villefranche-Sur-Mer","Listes":{"libelle":"Listes","url":"http:\/\/elections.interieur.gouv.fr\/MN2014\/006\/C1006159.html"},"resultat":{"libelle":"R&eacute;sultats re&ccedil;us 1er tour","url":"http:\/\/elections.interieur.gouv.fr\/MN2014\/006\/006159.html"}},"9":{"nom":"Villeneuve-D'Entraunes","Listes":{"libelle":"Candidats (Scrutin majoritaire)","url":"http:\/\/elections.interieur.gouv.fr\/MN2014\/006\/C1006160.html"},"resultat":{"libelle":"R&eacute;sultats re&ccedil;us 1er tour","url":"http:\/\/elections.interieur.gouv.fr\/MN2014\/006\/006160.html"}},"10":{"nom":"Villeneuve-Loubet","Listes":{"libelle":"Listes","url":"http:\/\/elections.interieur.gouv.fr\/MN2014\/006\/C1006161.html"},"resultat":{"libelle":"R&eacute;sultats re&ccedil;us 1er tour","url":"http:\/\/elections.interieur.gouv.fr\/MN2014\/006\/006161.html"}}}}}}}