{"45":{"url":"http:\/\/elections.interieur.gouv.fr\/MN2014\/045\/index.html","libelle":"45 - LOIRET","ListeVilles":{"1":{"url":"http:\/\/elections.interieur.gouv.fr\/MN2014\/045\/045A.html","libelle":"A","villes":{"1":{"nom":"Adon","Listes":{"libelle":"Candidats (Scrutin majoritaire)","url":"http:\/\/elections.interieur.gouv.fr\/MN2014\/045\/C1045001.html"},"resultat":{"libelle":"R&eacute;sultats re&ccedil;us 1er tour","url":"http:\/\/elections.interieur.gouv.fr\/MN2014\/045\/045001.html"}},"2":{"nom":"Aillant-Sur-Milleron","Listes":{"libelle":"Candidats (Scrutin majoritaire)","url":"http:\/\/elections.interieur.gouv.fr\/MN2014\/045\/C1045002.html"},"resultat":{"libelle":"R&eacute;sultats re&ccedil;us 1er tour","url":"http:\/\/elections.interieur.gouv.fr\/MN2014\/045\/045002.html"}},"3":{"nom":"Amilly","Listes":{"libelle":"Listes","url":"http:\/\/elections.interieur.gouv.fr\/MN2014\/045\/C1045004.html"},"resultat":{"libelle":"R&eacute;sultats re&ccedil;us 1er tour","url":"http:\/\/elections.interieur.gouv.fr\/MN2014\/045\/045004.html"}},"4":{"nom":"Andonville","Listes":{"libelle":"Candidats (Scrutin majoritaire)","url":"http:\/\/elections.interieur.gouv.fr\/MN2014\/045\/C1045005.html"},"resultat":{"libelle":"R&eacute;sultats re&ccedil;us 1er tour","url":"http:\/\/elections.interieur.gouv.fr\/MN2014\/045\/045005.html"}},"5":{"nom":"Ardon","Listes":{"libelle":"Listes","url":"http:\/\/elections.interieur.gouv.fr\/MN2014\/045\/C1045006.html"},"resultat":{"libelle":"R&eacute;sultats re&ccedil;us 1er tour","url":"http:\/\/elections.interieur.gouv.fr\/MN2014\/045\/045006.html"}},"6":{"nom":"Artenay","Listes":{"libelle":"Listes","url":"http:\/\/elections.interieur.gouv.fr\/MN2014\/045\/C1045008.html"},"resultat":{"libelle":"R&eacute;sultats re&ccedil;us 1er tour","url":"http:\/\/elections.interieur.gouv.fr\/MN2014\/045\/045008.html"}},"7":{"nom":"Asch&egrave;res-Le-March&eacute;","Listes":{"libelle":"Listes","url":"http:\/\/elections.interieur.gouv.fr\/MN2014\/045\/C1045009.html"},"resultat":{"libelle":"R&eacute;sultats re&ccedil;us 1er tour","url":"http:\/\/elections.interieur.gouv.fr\/MN2014\/045\/045009.html"}},"8":{"nom":"Ascoux","Listes":{"libelle":"Candidats (Scrutin majoritaire)","url":"http:\/\/elections.interieur.gouv.fr\/MN2014\/045\/C1045010.html"},"resultat":{"libelle":"R&eacute;sultats re&ccedil;us 1er tour","url":"http:\/\/elections.interieur.gouv.fr\/MN2014\/045\/045010.html"}},"9":{"nom":"Attray","Listes":{"libelle":"Candidats (Scrutin majoritaire)","url":"http:\/\/elections.interieur.gouv.fr\/MN2014\/045\/C1045011.html"},"resultat":{"libelle":"R&eacute;sultats re&ccedil;us 1er tour","url":"http:\/\/elections.interieur.gouv.fr\/MN2014\/045\/045011.html"}},"10":{"nom":"Audeville","Listes":{"libelle":"Candidats (Scrutin majoritaire)","url":"http:\/\/elections.interieur.gouv.fr\/MN2014\/045\/C1045012.html"},"resultat":{"libelle":"R&eacute;sultats re&ccedil;us 1er tour","url":"http:\/\/elections.interieur.gouv.fr\/MN2014\/045\/045012.html"}},"11":{"nom":"Augerville-La-Rivi&egrave;re","Listes":{"libelle":"Candidats (Scrutin majoritaire)","url":"http:\/\/elections.interieur.gouv.fr\/MN2014\/045\/C1045013.html"},"resultat":{"libelle":"R&eacute;sultats re&ccedil;us 1er tour","url":"http:\/\/elections.interieur.gouv.fr\/MN2014\/045\/045013.html"}},"12":{"nom":"Aulnay-La-Rivi&egrave;re","Listes":{"libelle":"Candidats (Scrutin majoritaire)","url":"http:\/\/elections.interieur.gouv.fr\/MN2014\/045\/C1045014.html"},"resultat":{"libelle":"R&eacute;sultats re&ccedil;us 1er tour","url":"http:\/\/elections.interieur.gouv.fr\/MN2014\/045\/045014.html"}},"13":{"nom":"Autruy-Sur-Juine","Listes":{"libelle":"Candidats (Scrutin majoritaire)","url":"http:\/\/elections.interieur.gouv.fr\/MN2014\/045\/C1045015.html"},"resultat":{"libelle":"R&eacute;sultats re&ccedil;us 1er tour","url":"http:\/\/elections.interieur.gouv.fr\/MN2014\/045\/045015.html"}},"14":{"nom":"Autry-Le-Ch&acirc;tel","Listes":{"libelle":"Listes","url":"http:\/\/elections.interieur.gouv.fr\/MN2014\/045\/C1045016.html"},"resultat":{"libelle":"R&eacute;sultats re&ccedil;us 1er tour","url":"http:\/\/elections.interieur.gouv.fr\/MN2014\/045\/045016.html"}},"15":{"nom":"Auvilliers-En-G&acirc;tinais","Listes":{"libelle":"Candidats (Scrutin majoritaire)","url":"http:\/\/elections.interieur.gouv.fr\/MN2014\/045\/C1045017.html"},"resultat":{"libelle":"R&eacute;sultats re&ccedil;us 1er tour","url":"http:\/\/elections.interieur.gouv.fr\/MN2014\/045\/045017.html"}},"16":{"nom":"Auxy","Listes":{"libelle":"Candidats (Scrutin majoritaire)","url":"http:\/\/elections.interieur.gouv.fr\/MN2014\/045\/C1045018.html"},"resultat":{"libelle":"R&eacute;sultats re&ccedil;us 1er tour","url":"http:\/\/elections.interieur.gouv.fr\/MN2014\/045\/045018.html"}}}},"2":{"url":"http:\/\/elections.interieur.gouv.fr\/MN2014\/045\/045B.html","libelle":"B","villes":{"1":{"nom":"Baccon","Listes":{"libelle":"Candidats (Scrutin majoritaire)","url":"http:\/\/elections.interieur.gouv.fr\/MN2014\/045\/C1045019.html"},"resultat":{"libelle":"R&eacute;sultats re&ccedil;us 1er tour","url":"http:\/\/elections.interieur.gouv.fr\/MN2014\/045\/045019.html"}},"2":{"nom":"Barville-En-G&acirc;tinais","Listes":{"libelle":"Candidats (Scrutin majoritaire)","url":"http:\/\/elections.interieur.gouv.fr\/MN2014\/045\/C1045021.html"},"resultat":{"libelle":"R&eacute;sultats re&ccedil;us 1er tour","url":"http:\/\/elections.interieur.gouv.fr\/MN2014\/045\/045021.html"}},"3":{"nom":"Batilly-En-G&acirc;tinais","Listes":{"libelle":"Candidats (Scrutin majoritaire)","url":"http:\/\/elections.interieur.gouv.fr\/MN2014\/045\/C1045022.html"},"resultat":{"libelle":"R&eacute;sultats re&ccedil;us 1er tour","url":"http:\/\/elections.interieur.gouv.fr\/MN2014\/045\/045022.html"}},"4":{"nom":"Batilly-En-Puisaye","Listes":{"libelle":"Candidats (Scrutin majoritaire)","url":"http:\/\/elections.interieur.gouv.fr\/MN2014\/045\/C1045023.html"},"resultat":{"libelle":"R&eacute;sultats re&ccedil;us 1er tour","url":"http:\/\/elections.interieur.gouv.fr\/MN2014\/045\/045023.html"}},"5":{"nom":"Baule","Listes":{"libelle":"Listes","url":"http:\/\/elections.interieur.gouv.fr\/MN2014\/045\/C1045024.html"},"resultat":{"libelle":"R&eacute;sultats re&ccedil;us 1er tour","url":"http:\/\/elections.interieur.gouv.fr\/MN2014\/045\/045024.html"}},"6":{"nom":"Bazoches-Les-Gallerandes","Listes":{"libelle":"Listes","url":"http:\/\/elections.interieur.gouv.fr\/MN2014\/045\/C1045025.html"},"resultat":{"libelle":"R&eacute;sultats re&ccedil;us 1er tour","url":"http:\/\/elections.interieur.gouv.fr\/MN2014\/045\/045025.html"}},"7":{"nom":"Bazoches-Sur-Le-Betz","Listes":{"libelle":"Candidats (Scrutin majoritaire)","url":"http:\/\/elections.interieur.gouv.fr\/MN2014\/045\/C1045026.html"},"resultat":{"libelle":"R&eacute;sultats re&ccedil;us 1er tour","url":"http:\/\/elections.interieur.gouv.fr\/MN2014\/045\/045026.html"}},"8":{"nom":"Beauchamps-Sur-Huillard","Listes":{"libelle":"Candidats (Scrutin majoritaire)","url":"http:\/\/elections.interieur.gouv.fr\/MN2014\/045\/C1045027.html"},"resultat":{"libelle":"R&eacute;sultats re&ccedil;us 1er tour","url":"http:\/\/elections.interieur.gouv.fr\/MN2014\/045\/045027.html"}},"9":{"nom":"Beaugency","Listes":{"libelle":"Listes","url":"http:\/\/elections.interieur.gouv.fr\/MN2014\/045\/C1045028.html"},"resultat":{"libelle":"R&eacute;sultats re&ccedil;us 1er tour","url":"http:\/\/elections.interieur.gouv.fr\/MN2014\/045\/045028.html"}},"10":{"nom":"Beaulieu-Sur-Loire","Listes":{"libelle":"Listes","url":"http:\/\/elections.interieur.gouv.fr\/MN2014\/045\/C1045029.html"},"resultat":{"libelle":"R&eacute;sultats re&ccedil;us 1er tour","url":"http:\/\/elections.interieur.gouv.fr\/MN2014\/045\/045029.html"}},"11":{"nom":"Beaune-La-Rolande","Listes":{"libelle":"Listes","url":"http:\/\/elections.interieur.gouv.fr\/MN2014\/045\/C1045030.html"},"resultat":{"libelle":"R&eacute;sultats re&ccedil;us 1er tour","url":"http:\/\/elections.interieur.gouv.fr\/MN2014\/045\/045030.html"}},"12":{"nom":"Bellegarde","Listes":{"libelle":"Listes","url":"http:\/\/elections.interieur.gouv.fr\/MN2014\/045\/C1045031.html"},"resultat":{"libelle":"R&eacute;sultats re&ccedil;us 1er tour","url":"http:\/\/elections.interieur.gouv.fr\/MN2014\/045\/045031.html"}},"13":{"nom":"Bo&euml;sse","Listes":{"libelle":"Candidats (Scrutin majoritaire)","url":"http:\/\/elections.interieur.gouv.fr\/MN2014\/045\/C1045033.html"},"resultat":{"libelle":"R&eacute;sultats re&ccedil;us 1er tour","url":"http:\/\/elections.interieur.gouv.fr\/MN2014\/045\/045033.html"}},"14":{"nom":"Boigny-Sur-Bionne","Listes":{"libelle":"Listes","url":"http:\/\/elections.interieur.gouv.fr\/MN2014\/045\/C1045034.html"},"resultat":{"libelle":"R&eacute;sultats re&ccedil;us 1er tour","url":"http:\/\/elections.interieur.gouv.fr\/MN2014\/045\/045034.html"}},"15":{"nom":"Boiscommun","Listes":{"libelle":"Listes","url":"http:\/\/elections.interieur.gouv.fr\/MN2014\/045\/C1045035.html"},"resultat":{"libelle":"R&eacute;sultats re&ccedil;us 1er tour","url":"http:\/\/elections.interieur.gouv.fr\/MN2014\/045\/045035.html"}},"16":{"nom":"Boismorand","Listes":{"libelle":"Candidats (Scrutin majoritaire)","url":"http:\/\/elections.interieur.gouv.fr\/MN2014\/045\/C1045036.html"},"resultat":{"libelle":"R&eacute;sultats re&ccedil;us 1er tour","url":"http:\/\/elections.interieur.gouv.fr\/MN2014\/045\/045036.html"}},"17":{"nom":"Boisseaux","Listes":{"libelle":"Candidats (Scrutin majoritaire)","url":"http:\/\/elections.interieur.gouv.fr\/MN2014\/045\/C1045037.html"},"resultat":{"libelle":"R&eacute;sultats re&ccedil;us 1er tour","url":"http:\/\/elections.interieur.gouv.fr\/MN2014\/045\/045037.html"}},"18":{"nom":"Bondaroy","Listes":{"libelle":"Candidats (Scrutin majoritaire)","url":"http:\/\/elections.interieur.gouv.fr\/MN2014\/045\/C1045038.html"},"resultat":{"libelle":"R&eacute;sultats re&ccedil;us 1er tour","url":"http:\/\/elections.interieur.gouv.fr\/MN2014\/045\/045038.html"}},"19":{"nom":"Bonn&eacute;e","Listes":{"libelle":"Candidats (Scrutin majoritaire)","url":"http:\/\/elections.interieur.gouv.fr\/MN2014\/045\/C1045039.html"},"resultat":{"libelle":"R&eacute;sultats re&ccedil;us 1er tour","url":"http:\/\/elections.interieur.gouv.fr\/MN2014\/045\/045039.html"}},"20":{"nom":"Bonny-Sur-Loire","Listes":{"libelle":"Listes","url":"http:\/\/elections.interieur.gouv.fr\/MN2014\/045\/C1045040.html"},"resultat":{"libelle":"R&eacute;sultats re&ccedil;us 1er tour","url":"http:\/\/elections.interieur.gouv.fr\/MN2014\/045\/045040.html"}},"21":{"nom":"Bordeaux-En-G&acirc;tinais","Listes":{"libelle":"Candidats (Scrutin majoritaire)","url":"http:\/\/elections.interieur.gouv.fr\/MN2014\/045\/C1045041.html"},"resultat":{"libelle":"R&eacute;sultats re&ccedil;us 1er tour","url":"http:\/\/elections.interieur.gouv.fr\/MN2014\/045\/045041.html"}},"22":{"nom":"Bou","Listes":{"libelle":"Candidats (Scrutin majoritaire)","url":"http:\/\/elections.interieur.gouv.fr\/MN2014\/045\/C1045043.html"},"resultat":{"libelle":"R&eacute;sultats re&ccedil;us 1er tour","url":"http:\/\/elections.interieur.gouv.fr\/MN2014\/045\/045043.html"}},"23":{"nom":"Bougy-Lez-Neuville","Listes":{"libelle":"Candidats (Scrutin majoritaire)","url":"http:\/\/elections.interieur.gouv.fr\/MN2014\/045\/C1045044.html"},"resultat":{"libelle":"R&eacute;sultats re&ccedil;us 1er tour","url":"http:\/\/elections.interieur.gouv.fr\/MN2014\/045\/045044.html"}},"24":{"nom":"Bouilly-En-G&acirc;tinais","Listes":{"libelle":"Candidats (Scrutin majoritaire)","url":"http:\/\/elections.interieur.gouv.fr\/MN2014\/045\/C1045045.html"},"resultat":{"libelle":"R&eacute;sultats re&ccedil;us 1er tour","url":"http:\/\/elections.interieur.gouv.fr\/MN2014\/045\/045045.html"}},"25":{"nom":"Boulay-Les-Barres","Listes":{"libelle":"Listes","url":"http:\/\/elections.interieur.gouv.fr\/MN2014\/045\/C1045046.html"},"resultat":{"libelle":"R&eacute;sultats re&ccedil;us 1er tour","url":"http:\/\/elections.interieur.gouv.fr\/MN2014\/045\/045046.html"}},"26":{"nom":"Bouzonville-Aux-Bois","Listes":{"libelle":"Candidats (Scrutin majoritaire)","url":"http:\/\/elections.interieur.gouv.fr\/MN2014\/045\/C1045047.html"},"resultat":{"libelle":"R&eacute;sultats re&ccedil;us 1er tour","url":"http:\/\/elections.interieur.gouv.fr\/MN2014\/045\/045047.html"}},"27":{"nom":"Bouzy-La-For&ecirc;t","Listes":{"libelle":"Listes","url":"http:\/\/elections.interieur.gouv.fr\/MN2014\/045\/C1045049.html"},"resultat":{"libelle":"R&eacute;sultats re&ccedil;us 1er tour","url":"http:\/\/elections.interieur.gouv.fr\/MN2014\/045\/045049.html"}},"28":{"nom":"Boynes","Listes":{"libelle":"Listes","url":"http:\/\/elections.interieur.gouv.fr\/MN2014\/045\/C1045050.html"},"resultat":{"libelle":"R&eacute;sultats re&ccedil;us 1er tour","url":"http:\/\/elections.interieur.gouv.fr\/MN2014\/045\/045050.html"}},"29":{"nom":"Bray-En-Val","Listes":{"libelle":"Listes","url":"http:\/\/elections.interieur.gouv.fr\/MN2014\/045\/C1045051.html"},"resultat":{"libelle":"R&eacute;sultats re&ccedil;us 1er tour","url":"http:\/\/elections.interieur.gouv.fr\/MN2014\/045\/045051.html"}},"30":{"nom":"Breteau","Listes":{"libelle":"Candidats (Scrutin majoritaire)","url":"http:\/\/elections.interieur.gouv.fr\/MN2014\/045\/C1045052.html"},"resultat":{"libelle":"R&eacute;sultats re&ccedil;us 1er tour","url":"http:\/\/elections.interieur.gouv.fr\/MN2014\/045\/045052.html"}},"31":{"nom":"Briare","Listes":{"libelle":"Listes","url":"http:\/\/elections.interieur.gouv.fr\/MN2014\/045\/C1045053.html"},"resultat":{"libelle":"R&eacute;sultats re&ccedil;us 1er tour","url":"http:\/\/elections.interieur.gouv.fr\/MN2014\/045\/045053.html"}},"32":{"nom":"Briarres-Sur-Essonne","Listes":{"libelle":"Candidats (Scrutin majoritaire)","url":"http:\/\/elections.interieur.gouv.fr\/MN2014\/045\/C1045054.html"},"resultat":{"libelle":"R&eacute;sultats re&ccedil;us 1er tour","url":"http:\/\/elections.interieur.gouv.fr\/MN2014\/045\/045054.html"}},"33":{"nom":"Bricy","Listes":{"libelle":"Candidats (Scrutin majoritaire)","url":"http:\/\/elections.interieur.gouv.fr\/MN2014\/045\/C1045055.html"},"resultat":{"libelle":"R&eacute;sultats re&ccedil;us 1er tour","url":"http:\/\/elections.interieur.gouv.fr\/MN2014\/045\/045055.html"}},"34":{"nom":"Bromeilles","Listes":{"libelle":"Candidats (Scrutin majoritaire)","url":"http:\/\/elections.interieur.gouv.fr\/MN2014\/045\/C1045056.html"},"resultat":{"libelle":"R&eacute;sultats re&ccedil;us 1er tour","url":"http:\/\/elections.interieur.gouv.fr\/MN2014\/045\/045056.html"}},"35":{"nom":"Bucy-Le-Roi","Listes":{"libelle":"Candidats (Scrutin majoritaire)","url":"http:\/\/elections.interieur.gouv.fr\/MN2014\/045\/C1045058.html"},"resultat":{"libelle":"R&eacute;sultats re&ccedil;us 1er tour","url":"http:\/\/elections.interieur.gouv.fr\/MN2014\/045\/045058.html"}},"36":{"nom":"Bucy-Saint-Liphard","Listes":{"libelle":"Candidats (Scrutin majoritaire)","url":"http:\/\/elections.interieur.gouv.fr\/MN2014\/045\/C1045059.html"},"resultat":{"libelle":"R&eacute;sultats re&ccedil;us 1er tour","url":"http:\/\/elections.interieur.gouv.fr\/MN2014\/045\/045059.html"}}}},"3":{"url":"http:\/\/elections.interieur.gouv.fr\/MN2014\/045\/045C.html","libelle":"C","villes":{"1":{"nom":"Cepoy","Listes":{"libelle":"Listes","url":"http:\/\/elections.interieur.gouv.fr\/MN2014\/045\/C1045061.html"},"resultat":{"libelle":"R&eacute;sultats re&ccedil;us 1er tour","url":"http:\/\/elections.interieur.gouv.fr\/MN2014\/045\/045061.html"}},"2":{"nom":"Cercottes","Listes":{"libelle":"Listes","url":"http:\/\/elections.interieur.gouv.fr\/MN2014\/045\/C1045062.html"},"resultat":{"libelle":"R&eacute;sultats re&ccedil;us 1er tour","url":"http:\/\/elections.interieur.gouv.fr\/MN2014\/045\/045062.html"}},"3":{"nom":"Cerdon","Listes":{"libelle":"Listes","url":"http:\/\/elections.interieur.gouv.fr\/MN2014\/045\/C1045063.html"},"resultat":{"libelle":"R&eacute;sultats re&ccedil;us 1er tour","url":"http:\/\/elections.interieur.gouv.fr\/MN2014\/045\/045063.html"}},"4":{"nom":"Cernoy-En-Berry","Listes":{"libelle":"Candidats (Scrutin majoritaire)","url":"http:\/\/elections.interieur.gouv.fr\/MN2014\/045\/C1045064.html"},"resultat":{"libelle":"R&eacute;sultats re&ccedil;us 1er tour","url":"http:\/\/elections.interieur.gouv.fr\/MN2014\/045\/045064.html"}},"5":{"nom":"C&eacute;sarville-Dossainville","Listes":{"libelle":"Candidats (Scrutin majoritaire)","url":"http:\/\/elections.interieur.gouv.fr\/MN2014\/045\/C1045065.html"},"resultat":{"libelle":"R&eacute;sultats re&ccedil;us 1er tour","url":"http:\/\/elections.interieur.gouv.fr\/MN2014\/045\/045065.html"}},"6":{"nom":"Chailly-En-G&acirc;tinais","Listes":{"libelle":"Candidats (Scrutin majoritaire)","url":"http:\/\/elections.interieur.gouv.fr\/MN2014\/045\/C1045066.html"},"resultat":{"libelle":"R&eacute;sultats re&ccedil;us 1er tour","url":"http:\/\/elections.interieur.gouv.fr\/MN2014\/045\/045066.html"}},"7":{"nom":"Chaingy","Listes":{"libelle":"Listes","url":"http:\/\/elections.interieur.gouv.fr\/MN2014\/045\/C1045067.html"},"resultat":{"libelle":"R&eacute;sultats re&ccedil;us 1er tour","url":"http:\/\/elections.interieur.gouv.fr\/MN2014\/045\/045067.html"}},"8":{"nom":"Ch&acirc;lette-Sur-Loing","Listes":{"libelle":"Listes","url":"http:\/\/elections.interieur.gouv.fr\/MN2014\/045\/C1045068.html"},"resultat":{"libelle":"R&eacute;sultats re&ccedil;us 1er tour","url":"http:\/\/elections.interieur.gouv.fr\/MN2014\/045\/045068.html"}},"9":{"nom":"Chambon-La-For&ecirc;t","Listes":{"libelle":"Candidats (Scrutin majoritaire)","url":"http:\/\/elections.interieur.gouv.fr\/MN2014\/045\/C1045069.html"},"resultat":{"libelle":"R&eacute;sultats re&ccedil;us 1er tour","url":"http:\/\/elections.interieur.gouv.fr\/MN2014\/045\/045069.html"}},"10":{"nom":"Champoulet","Listes":{"libelle":"Candidats (Scrutin majoritaire)","url":"http:\/\/elections.interieur.gouv.fr\/MN2014\/045\/C1045070.html"},"resultat":{"libelle":"R&eacute;sultats re&ccedil;us 1er tour","url":"http:\/\/elections.interieur.gouv.fr\/MN2014\/045\/045070.html"}},"11":{"nom":"Chanteau","Listes":{"libelle":"Listes","url":"http:\/\/elections.interieur.gouv.fr\/MN2014\/045\/C1045072.html"},"resultat":{"libelle":"R&eacute;sultats re&ccedil;us 1er tour","url":"http:\/\/elections.interieur.gouv.fr\/MN2014\/045\/045072.html"}},"12":{"nom":"Chantecoq","Listes":{"libelle":"Candidats (Scrutin majoritaire)","url":"http:\/\/elections.interieur.gouv.fr\/MN2014\/045\/C1045073.html"},"resultat":{"libelle":"R&eacute;sultats re&ccedil;us 1er tour","url":"http:\/\/elections.interieur.gouv.fr\/MN2014\/045\/045073.html"}},"13":{"nom":"Chapelon","Listes":{"libelle":"Candidats (Scrutin majoritaire)","url":"http:\/\/elections.interieur.gouv.fr\/MN2014\/045\/C1045078.html"},"resultat":{"libelle":"R&eacute;sultats re&ccedil;us 1er tour","url":"http:\/\/elections.interieur.gouv.fr\/MN2014\/045\/045078.html"}},"14":{"nom":"Charmont-En-Beauce","Listes":{"libelle":"Candidats (Scrutin majoritaire)","url":"http:\/\/elections.interieur.gouv.fr\/MN2014\/045\/C1045080.html"},"resultat":{"libelle":"R&eacute;sultats re&ccedil;us 1er tour","url":"http:\/\/elections.interieur.gouv.fr\/MN2014\/045\/045080.html"}},"15":{"nom":"Charsonville","Listes":{"libelle":"Candidats (Scrutin majoritaire)","url":"http:\/\/elections.interieur.gouv.fr\/MN2014\/045\/C1045081.html"},"resultat":{"libelle":"R&eacute;sultats re&ccedil;us 1er tour","url":"http:\/\/elections.interieur.gouv.fr\/MN2014\/045\/045081.html"}},"16":{"nom":"Ch&acirc;teauneuf-Sur-Loire","Listes":{"libelle":"Listes","url":"http:\/\/elections.interieur.gouv.fr\/MN2014\/045\/C1045082.html"},"resultat":{"libelle":"R&eacute;sultats re&ccedil;us 1er tour","url":"http:\/\/elections.interieur.gouv.fr\/MN2014\/045\/045082.html"}},"17":{"nom":"Ch&acirc;teau-Renard","Listes":{"libelle":"Listes","url":"http:\/\/elections.interieur.gouv.fr\/MN2014\/045\/C1045083.html"},"resultat":{"libelle":"R&eacute;sultats re&ccedil;us 1er tour","url":"http:\/\/elections.interieur.gouv.fr\/MN2014\/045\/045083.html"}},"18":{"nom":"Ch&acirc;tenoy","Listes":{"libelle":"Candidats (Scrutin majoritaire)","url":"http:\/\/elections.interieur.gouv.fr\/MN2014\/045\/C1045084.html"},"resultat":{"libelle":"R&eacute;sultats re&ccedil;us 1er tour","url":"http:\/\/elections.interieur.gouv.fr\/MN2014\/045\/045084.html"}},"19":{"nom":"Ch&acirc;tillon-Coligny","Listes":{"libelle":"Listes","url":"http:\/\/elections.interieur.gouv.fr\/MN2014\/045\/C1045085.html"},"resultat":{"libelle":"R&eacute;sultats re&ccedil;us 1er tour","url":"http:\/\/elections.interieur.gouv.fr\/MN2014\/045\/045085.html"}},"20":{"nom":"Ch&acirc;tillon-Le-Roi","Listes":{"libelle":"Candidats (Scrutin majoritaire)","url":"http:\/\/elections.interieur.gouv.fr\/MN2014\/045\/C1045086.html"},"resultat":{"libelle":"R&eacute;sultats re&ccedil;us 1er tour","url":"http:\/\/elections.interieur.gouv.fr\/MN2014\/045\/045086.html"}},"21":{"nom":"Ch&acirc;tillon-Sur-Loire","Listes":{"libelle":"Listes","url":"http:\/\/elections.interieur.gouv.fr\/MN2014\/045\/C1045087.html"},"resultat":{"libelle":"R&eacute;sultats re&ccedil;us 1er tour","url":"http:\/\/elections.interieur.gouv.fr\/MN2014\/045\/045087.html"}},"22":{"nom":"Chaussy","Listes":{"libelle":"Candidats (Scrutin majoritaire)","url":"http:\/\/elections.interieur.gouv.fr\/MN2014\/045\/C1045088.html"},"resultat":{"libelle":"R&eacute;sultats re&ccedil;us 1er tour","url":"http:\/\/elections.interieur.gouv.fr\/MN2014\/045\/045088.html"}},"23":{"nom":"Ch&eacute;cy","Listes":{"libelle":"Listes","url":"http:\/\/elections.interieur.gouv.fr\/MN2014\/045\/C1045089.html"},"resultat":{"libelle":"R&eacute;sultats re&ccedil;us 1er tour","url":"http:\/\/elections.interieur.gouv.fr\/MN2014\/045\/045089.html"}},"24":{"nom":"Chevannes","Listes":{"libelle":"Candidats (Scrutin majoritaire)","url":"http:\/\/elections.interieur.gouv.fr\/MN2014\/045\/C1045091.html"},"resultat":{"libelle":"R&eacute;sultats re&ccedil;us 1er tour","url":"http:\/\/elections.interieur.gouv.fr\/MN2014\/045\/045091.html"}},"25":{"nom":"Chevillon-Sur-Huillard","Listes":{"libelle":"Listes","url":"http:\/\/elections.interieur.gouv.fr\/MN2014\/045\/C1045092.html"},"resultat":{"libelle":"R&eacute;sultats re&ccedil;us 1er tour","url":"http:\/\/elections.interieur.gouv.fr\/MN2014\/045\/045092.html"}},"26":{"nom":"Chevilly","Listes":{"libelle":"Listes","url":"http:\/\/elections.interieur.gouv.fr\/MN2014\/045\/C1045093.html"},"resultat":{"libelle":"R&eacute;sultats re&ccedil;us 1er tour","url":"http:\/\/elections.interieur.gouv.fr\/MN2014\/045\/045093.html"}},"27":{"nom":"Chevry-Sous-Le-Bignon","Listes":{"libelle":"Candidats (Scrutin majoritaire)","url":"http:\/\/elections.interieur.gouv.fr\/MN2014\/045\/C1045094.html"},"resultat":{"libelle":"R&eacute;sultats re&ccedil;us 1er tour","url":"http:\/\/elections.interieur.gouv.fr\/MN2014\/045\/045094.html"}},"28":{"nom":"Chilleurs-Aux-Bois","Listes":{"libelle":"Listes","url":"http:\/\/elections.interieur.gouv.fr\/MN2014\/045\/C1045095.html"},"resultat":{"libelle":"R&eacute;sultats re&ccedil;us 1er tour","url":"http:\/\/elections.interieur.gouv.fr\/MN2014\/045\/045095.html"}},"29":{"nom":"Chuelles","Listes":{"libelle":"Listes","url":"http:\/\/elections.interieur.gouv.fr\/MN2014\/045\/C1045097.html"},"resultat":{"libelle":"R&eacute;sultats re&ccedil;us 1er tour","url":"http:\/\/elections.interieur.gouv.fr\/MN2014\/045\/045097.html"}},"30":{"nom":"Cl&eacute;ry-Saint-Andr&eacute;","Listes":{"libelle":"Listes","url":"http:\/\/elections.interieur.gouv.fr\/MN2014\/045\/C1045098.html"},"resultat":{"libelle":"R&eacute;sultats re&ccedil;us 1er tour","url":"http:\/\/elections.interieur.gouv.fr\/MN2014\/045\/045098.html"}},"31":{"nom":"Coinces","Listes":{"libelle":"Candidats (Scrutin majoritaire)","url":"http:\/\/elections.interieur.gouv.fr\/MN2014\/045\/C1045099.html"},"resultat":{"libelle":"R&eacute;sultats re&ccedil;us 1er tour","url":"http:\/\/elections.interieur.gouv.fr\/MN2014\/045\/045099.html"}},"32":{"nom":"Combleux","Listes":{"libelle":"Candidats (Scrutin majoritaire)","url":"http:\/\/elections.interieur.gouv.fr\/MN2014\/045\/C1045100.html"},"resultat":{"libelle":"R&eacute;sultats re&ccedil;us 1er tour","url":"http:\/\/elections.interieur.gouv.fr\/MN2014\/045\/045100.html"}},"33":{"nom":"Combreux","Listes":{"libelle":"Candidats (Scrutin majoritaire)","url":"http:\/\/elections.interieur.gouv.fr\/MN2014\/045\/C1045101.html"},"resultat":{"libelle":"R&eacute;sultats re&ccedil;us 1er tour","url":"http:\/\/elections.interieur.gouv.fr\/MN2014\/045\/045101.html"}},"34":{"nom":"Conflans-Sur-Loing","Listes":{"libelle":"Candidats (Scrutin majoritaire)","url":"http:\/\/elections.interieur.gouv.fr\/MN2014\/045\/C1045102.html"},"resultat":{"libelle":"R&eacute;sultats re&ccedil;us 1er tour","url":"http:\/\/elections.interieur.gouv.fr\/MN2014\/045\/045102.html"}},"35":{"nom":"Corbeilles","Listes":{"libelle":"Listes","url":"http:\/\/elections.interieur.gouv.fr\/MN2014\/045\/C1045103.html"},"resultat":{"libelle":"R&eacute;sultats re&ccedil;us 1er tour","url":"http:\/\/elections.interieur.gouv.fr\/MN2014\/045\/045103.html"}},"36":{"nom":"Corquilleroy","Listes":{"libelle":"Listes","url":"http:\/\/elections.interieur.gouv.fr\/MN2014\/045\/C1045104.html"},"resultat":{"libelle":"R&eacute;sultats re&ccedil;us 1er tour","url":"http:\/\/elections.interieur.gouv.fr\/MN2014\/045\/045104.html"}},"37":{"nom":"Cortrat","Listes":{"libelle":"Candidats (Scrutin majoritaire)","url":"http:\/\/elections.interieur.gouv.fr\/MN2014\/045\/C1045105.html"},"resultat":{"libelle":"R&eacute;sultats re&ccedil;us 1er tour","url":"http:\/\/elections.interieur.gouv.fr\/MN2014\/045\/045105.html"}},"38":{"nom":"Coudray","Listes":{"libelle":"Candidats (Scrutin majoritaire)","url":"http:\/\/elections.interieur.gouv.fr\/MN2014\/045\/C1045106.html"},"resultat":{"libelle":"R&eacute;sultats re&ccedil;us 1er tour","url":"http:\/\/elections.interieur.gouv.fr\/MN2014\/045\/045106.html"}},"39":{"nom":"Coudroy","Listes":{"libelle":"Candidats (Scrutin majoritaire)","url":"http:\/\/elections.interieur.gouv.fr\/MN2014\/045\/C1045107.html"},"resultat":{"libelle":"R&eacute;sultats re&ccedil;us 1er tour","url":"http:\/\/elections.interieur.gouv.fr\/MN2014\/045\/045107.html"}},"40":{"nom":"Coullons","Listes":{"libelle":"Listes","url":"http:\/\/elections.interieur.gouv.fr\/MN2014\/045\/C1045108.html"},"resultat":{"libelle":"R&eacute;sultats re&ccedil;us 1er tour","url":"http:\/\/elections.interieur.gouv.fr\/MN2014\/045\/045108.html"}},"41":{"nom":"Coulmiers","Listes":{"libelle":"Candidats (Scrutin majoritaire)","url":"http:\/\/elections.interieur.gouv.fr\/MN2014\/045\/C1045109.html"},"resultat":{"libelle":"R&eacute;sultats re&ccedil;us 1er tour","url":"http:\/\/elections.interieur.gouv.fr\/MN2014\/045\/045109.html"}},"42":{"nom":"Courcelles","Listes":{"libelle":"Candidats (Scrutin majoritaire)","url":"http:\/\/elections.interieur.gouv.fr\/MN2014\/045\/C1045110.html"},"resultat":{"libelle":"R&eacute;sultats re&ccedil;us 1er tour","url":"http:\/\/elections.interieur.gouv.fr\/MN2014\/045\/045110.html"}},"43":{"nom":"Courcy-Aux-Loges","Listes":{"libelle":"Candidats (Scrutin majoritaire)","url":"http:\/\/elections.interieur.gouv.fr\/MN2014\/045\/C1045111.html"},"resultat":{"libelle":"R&eacute;sultats re&ccedil;us 1er tour","url":"http:\/\/elections.interieur.gouv.fr\/MN2014\/045\/045111.html"}},"44":{"nom":"Courtemaux","Listes":{"libelle":"Candidats (Scrutin majoritaire)","url":"http:\/\/elections.interieur.gouv.fr\/MN2014\/045\/C1045113.html"},"resultat":{"libelle":"R&eacute;sultats re&ccedil;us 1er tour","url":"http:\/\/elections.interieur.gouv.fr\/MN2014\/045\/045113.html"}},"45":{"nom":"Courtempierre","Listes":{"libelle":"Candidats (Scrutin majoritaire)","url":"http:\/\/elections.interieur.gouv.fr\/MN2014\/045\/C1045114.html"},"resultat":{"libelle":"R&eacute;sultats re&ccedil;us 1er tour","url":"http:\/\/elections.interieur.gouv.fr\/MN2014\/045\/045114.html"}},"46":{"nom":"Courtenay","Listes":{"libelle":"Listes","url":"http:\/\/elections.interieur.gouv.fr\/MN2014\/045\/C1045115.html"},"resultat":{"libelle":"R&eacute;sultats re&ccedil;us 1er tour","url":"http:\/\/elections.interieur.gouv.fr\/MN2014\/045\/045115.html"}},"47":{"nom":"Cravant","Listes":{"libelle":"Candidats (Scrutin majoritaire)","url":"http:\/\/elections.interieur.gouv.fr\/MN2014\/045\/C1045116.html"},"resultat":{"libelle":"R&eacute;sultats re&ccedil;us 1er tour","url":"http:\/\/elections.interieur.gouv.fr\/MN2014\/045\/045116.html"}},"48":{"nom":"Crottes-En-Pithiverais","Listes":{"libelle":"Candidats (Scrutin majoritaire)","url":"http:\/\/elections.interieur.gouv.fr\/MN2014\/045\/C1045118.html"},"resultat":{"libelle":"R&eacute;sultats re&ccedil;us 1er tour","url":"http:\/\/elections.interieur.gouv.fr\/MN2014\/045\/045118.html"}}}},"4":{"url":"http:\/\/elections.interieur.gouv.fr\/MN2014\/045\/045D.html","libelle":"D","villes":{"1":{"nom":"Dadonville","Listes":{"libelle":"Listes","url":"http:\/\/elections.interieur.gouv.fr\/MN2014\/045\/C1045119.html"},"resultat":{"libelle":"R&eacute;sultats re&ccedil;us 1er tour","url":"http:\/\/elections.interieur.gouv.fr\/MN2014\/045\/045119.html"}},"2":{"nom":"Dammarie-En-Puisaye","Listes":{"libelle":"Candidats (Scrutin majoritaire)","url":"http:\/\/elections.interieur.gouv.fr\/MN2014\/045\/C1045120.html"},"resultat":{"libelle":"R&eacute;sultats re&ccedil;us 1er tour","url":"http:\/\/elections.interieur.gouv.fr\/MN2014\/045\/045120.html"}},"3":{"nom":"Dammarie-Sur-Loing","Listes":{"libelle":"Candidats (Scrutin majoritaire)","url":"http:\/\/elections.interieur.gouv.fr\/MN2014\/045\/C1045121.html"},"resultat":{"libelle":"R&eacute;sultats re&ccedil;us 1er tour","url":"http:\/\/elections.interieur.gouv.fr\/MN2014\/045\/045121.html"}},"4":{"nom":"Dampierre-En-Burly","Listes":{"libelle":"Listes","url":"http:\/\/elections.interieur.gouv.fr\/MN2014\/045\/C1045122.html"},"resultat":{"libelle":"R&eacute;sultats re&ccedil;us 1er tour","url":"http:\/\/elections.interieur.gouv.fr\/MN2014\/045\/045122.html"}},"5":{"nom":"Darvoy","Listes":{"libelle":"Listes","url":"http:\/\/elections.interieur.gouv.fr\/MN2014\/045\/C1045123.html"},"resultat":{"libelle":"R&eacute;sultats re&ccedil;us 1er tour","url":"http:\/\/elections.interieur.gouv.fr\/MN2014\/045\/045123.html"}},"6":{"nom":"Desmont","Listes":{"libelle":"Candidats (Scrutin majoritaire)","url":"http:\/\/elections.interieur.gouv.fr\/MN2014\/045\/C1045124.html"},"resultat":{"libelle":"R&eacute;sultats re&ccedil;us 1er tour","url":"http:\/\/elections.interieur.gouv.fr\/MN2014\/045\/045124.html"}},"7":{"nom":"Dimancheville","Listes":{"libelle":"Candidats (Scrutin majoritaire)","url":"http:\/\/elections.interieur.gouv.fr\/MN2014\/045\/C1045125.html"},"resultat":{"libelle":"R&eacute;sultats re&ccedil;us 1er tour","url":"http:\/\/elections.interieur.gouv.fr\/MN2014\/045\/045125.html"}},"8":{"nom":"Donnery","Listes":{"libelle":"Listes","url":"http:\/\/elections.interieur.gouv.fr\/MN2014\/045\/C1045126.html"},"resultat":{"libelle":"R&eacute;sultats re&ccedil;us 1er tour","url":"http:\/\/elections.interieur.gouv.fr\/MN2014\/045\/045126.html"}},"9":{"nom":"Dordives","Listes":{"libelle":"Listes","url":"http:\/\/elections.interieur.gouv.fr\/MN2014\/045\/C1045127.html"},"resultat":{"libelle":"R&eacute;sultats re&ccedil;us 1er tour","url":"http:\/\/elections.interieur.gouv.fr\/MN2014\/045\/045127.html"}},"10":{"nom":"Douchy","Listes":{"libelle":"Listes","url":"http:\/\/elections.interieur.gouv.fr\/MN2014\/045\/C1045129.html"},"resultat":{"libelle":"R&eacute;sultats re&ccedil;us 1er tour","url":"http:\/\/elections.interieur.gouv.fr\/MN2014\/045\/045129.html"}},"11":{"nom":"Dry","Listes":{"libelle":"Listes","url":"http:\/\/elections.interieur.gouv.fr\/MN2014\/045\/C1045130.html"},"resultat":{"libelle":"R&eacute;sultats re&ccedil;us 1er tour","url":"http:\/\/elections.interieur.gouv.fr\/MN2014\/045\/045130.html"}}}},"5":{"url":"http:\/\/elections.interieur.gouv.fr\/MN2014\/045\/045E.html","libelle":"E","villes":{"1":{"nom":"Echilleuses","Listes":{"libelle":"Candidats (Scrutin majoritaire)","url":"http:\/\/elections.interieur.gouv.fr\/MN2014\/045\/C1045131.html"},"resultat":{"libelle":"R&eacute;sultats re&ccedil;us 1er tour","url":"http:\/\/elections.interieur.gouv.fr\/MN2014\/045\/045131.html"}},"2":{"nom":"Egry","Listes":{"libelle":"Candidats (Scrutin majoritaire)","url":"http:\/\/elections.interieur.gouv.fr\/MN2014\/045\/C1045132.html"},"resultat":{"libelle":"R&eacute;sultats re&ccedil;us 1er tour","url":"http:\/\/elections.interieur.gouv.fr\/MN2014\/045\/045132.html"}},"3":{"nom":"Engenville","Listes":{"libelle":"Candidats (Scrutin majoritaire)","url":"http:\/\/elections.interieur.gouv.fr\/MN2014\/045\/C1045133.html"},"resultat":{"libelle":"R&eacute;sultats re&ccedil;us 1er tour","url":"http:\/\/elections.interieur.gouv.fr\/MN2014\/045\/045133.html"}},"4":{"nom":"Epieds-En-Beauce","Listes":{"libelle":"Listes","url":"http:\/\/elections.interieur.gouv.fr\/MN2014\/045\/C1045134.html"},"resultat":{"libelle":"R&eacute;sultats re&ccedil;us 1er tour","url":"http:\/\/elections.interieur.gouv.fr\/MN2014\/045\/045134.html"}},"5":{"nom":"Erceville","Listes":{"libelle":"Candidats (Scrutin majoritaire)","url":"http:\/\/elections.interieur.gouv.fr\/MN2014\/045\/C1045135.html"},"resultat":{"libelle":"R&eacute;sultats re&ccedil;us 1er tour","url":"http:\/\/elections.interieur.gouv.fr\/MN2014\/045\/045135.html"}},"6":{"nom":"Ervauville","Listes":{"libelle":"Candidats (Scrutin majoritaire)","url":"http:\/\/elections.interieur.gouv.fr\/MN2014\/045\/C1045136.html"},"resultat":{"libelle":"R&eacute;sultats re&ccedil;us 1er tour","url":"http:\/\/elections.interieur.gouv.fr\/MN2014\/045\/045136.html"}},"7":{"nom":"Escrennes","Listes":{"libelle":"Candidats (Scrutin majoritaire)","url":"http:\/\/elections.interieur.gouv.fr\/MN2014\/045\/C1045137.html"},"resultat":{"libelle":"R&eacute;sultats re&ccedil;us 1er tour","url":"http:\/\/elections.interieur.gouv.fr\/MN2014\/045\/045137.html"}},"8":{"nom":"Escrignelles","Listes":{"libelle":"Candidats (Scrutin majoritaire)","url":"http:\/\/elections.interieur.gouv.fr\/MN2014\/045\/C1045138.html"},"resultat":{"libelle":"R&eacute;sultats re&ccedil;us 1er tour","url":"http:\/\/elections.interieur.gouv.fr\/MN2014\/045\/045138.html"}},"9":{"nom":"Estouy","Listes":{"libelle":"Candidats (Scrutin majoritaire)","url":"http:\/\/elections.interieur.gouv.fr\/MN2014\/045\/C1045139.html"},"resultat":{"libelle":"R&eacute;sultats re&ccedil;us 1er tour","url":"http:\/\/elections.interieur.gouv.fr\/MN2014\/045\/045139.html"}}}},"6":{"url":"http:\/\/elections.interieur.gouv.fr\/MN2014\/045\/045F.html","libelle":"F","villes":{"1":{"nom":"Faverelles","Listes":{"libelle":"Candidats (Scrutin majoritaire)","url":"http:\/\/elections.interieur.gouv.fr\/MN2014\/045\/C1045141.html"},"resultat":{"libelle":"R&eacute;sultats re&ccedil;us 1er tour","url":"http:\/\/elections.interieur.gouv.fr\/MN2014\/045\/045141.html"}},"2":{"nom":"Fay-Aux-Loges","Listes":{"libelle":"Listes","url":"http:\/\/elections.interieur.gouv.fr\/MN2014\/045\/C1045142.html"},"resultat":{"libelle":"R&eacute;sultats re&ccedil;us 1er tour","url":"http:\/\/elections.interieur.gouv.fr\/MN2014\/045\/045142.html"}},"3":{"nom":"Feins-En-G&acirc;tinais","Listes":{"libelle":"Candidats (Scrutin majoritaire)","url":"http:\/\/elections.interieur.gouv.fr\/MN2014\/045\/C1045143.html"},"resultat":{"libelle":"R&eacute;sultats re&ccedil;us 1er tour","url":"http:\/\/elections.interieur.gouv.fr\/MN2014\/045\/045143.html"}},"4":{"nom":"F&eacute;rolles","Listes":{"libelle":"Listes","url":"http:\/\/elections.interieur.gouv.fr\/MN2014\/045\/C1045144.html"},"resultat":{"libelle":"R&eacute;sultats re&ccedil;us 1er tour","url":"http:\/\/elections.interieur.gouv.fr\/MN2014\/045\/045144.html"}},"5":{"nom":"Ferri&egrave;res","Listes":{"libelle":"Listes","url":"http:\/\/elections.interieur.gouv.fr\/MN2014\/045\/C1045145.html"},"resultat":{"libelle":"R&eacute;sultats re&ccedil;us 1er tour","url":"http:\/\/elections.interieur.gouv.fr\/MN2014\/045\/045145.html"}},"6":{"nom":"Fleury-Les-Aubrais","Listes":{"libelle":"Listes","url":"http:\/\/elections.interieur.gouv.fr\/MN2014\/045\/C1045147.html"},"resultat":{"libelle":"R&eacute;sultats re&ccedil;us 1er tour","url":"http:\/\/elections.interieur.gouv.fr\/MN2014\/045\/045147.html"}},"7":{"nom":"Fontenay-Sur-Loing","Listes":{"libelle":"Listes","url":"http:\/\/elections.interieur.gouv.fr\/MN2014\/045\/C1045148.html"},"resultat":{"libelle":"R&eacute;sultats re&ccedil;us 1er tour","url":"http:\/\/elections.interieur.gouv.fr\/MN2014\/045\/045148.html"}},"8":{"nom":"Foucherolles","Listes":{"libelle":"Candidats (Scrutin majoritaire)","url":"http:\/\/elections.interieur.gouv.fr\/MN2014\/045\/C1045149.html"},"resultat":{"libelle":"R&eacute;sultats re&ccedil;us 1er tour","url":"http:\/\/elections.interieur.gouv.fr\/MN2014\/045\/045149.html"}},"9":{"nom":"Fr&eacute;ville-Du-G&acirc;tinais","Listes":{"libelle":"Candidats (Scrutin majoritaire)","url":"http:\/\/elections.interieur.gouv.fr\/MN2014\/045\/C1045150.html"},"resultat":{"libelle":"R&eacute;sultats re&ccedil;us 1er tour","url":"http:\/\/elections.interieur.gouv.fr\/MN2014\/045\/045150.html"}}}},"7":{"url":"http:\/\/elections.interieur.gouv.fr\/MN2014\/045\/045G.html","libelle":"G","villes":{"1":{"nom":"Gaubertin","Listes":{"libelle":"Candidats (Scrutin majoritaire)","url":"http:\/\/elections.interieur.gouv.fr\/MN2014\/045\/C1045151.html"},"resultat":{"libelle":"R&eacute;sultats re&ccedil;us 1er tour","url":"http:\/\/elections.interieur.gouv.fr\/MN2014\/045\/045151.html"}},"2":{"nom":"G&eacute;migny","Listes":{"libelle":"Candidats (Scrutin majoritaire)","url":"http:\/\/elections.interieur.gouv.fr\/MN2014\/045\/C1045152.html"},"resultat":{"libelle":"R&eacute;sultats re&ccedil;us 1er tour","url":"http:\/\/elections.interieur.gouv.fr\/MN2014\/045\/045152.html"}},"3":{"nom":"Germigny-Des-Pr&eacute;s","Listes":{"libelle":"Candidats (Scrutin majoritaire)","url":"http:\/\/elections.interieur.gouv.fr\/MN2014\/045\/C1045153.html"},"resultat":{"libelle":"R&eacute;sultats re&ccedil;us 1er tour","url":"http:\/\/elections.interieur.gouv.fr\/MN2014\/045\/045153.html"}},"4":{"nom":"Gidy","Listes":{"libelle":"Listes","url":"http:\/\/elections.interieur.gouv.fr\/MN2014\/045\/C1045154.html"},"resultat":{"libelle":"R&eacute;sultats re&ccedil;us 1er tour","url":"http:\/\/elections.interieur.gouv.fr\/MN2014\/045\/045154.html"}},"5":{"nom":"Gien","Listes":{"libelle":"Listes","url":"http:\/\/elections.interieur.gouv.fr\/MN2014\/045\/C1045155.html"},"resultat":{"libelle":"R&eacute;sultats re&ccedil;us 1er tour","url":"http:\/\/elections.interieur.gouv.fr\/MN2014\/045\/045155.html"}},"6":{"nom":"Girolles","Listes":{"libelle":"Candidats (Scrutin majoritaire)","url":"http:\/\/elections.interieur.gouv.fr\/MN2014\/045\/C1045156.html"},"resultat":{"libelle":"R&eacute;sultats re&ccedil;us 1er tour","url":"http:\/\/elections.interieur.gouv.fr\/MN2014\/045\/045156.html"}},"7":{"nom":"Givraines","Listes":{"libelle":"Candidats (Scrutin majoritaire)","url":"http:\/\/elections.interieur.gouv.fr\/MN2014\/045\/C1045157.html"},"resultat":{"libelle":"R&eacute;sultats re&ccedil;us 1er tour","url":"http:\/\/elections.interieur.gouv.fr\/MN2014\/045\/045157.html"}},"8":{"nom":"Gondreville","Listes":{"libelle":"Candidats (Scrutin majoritaire)","url":"http:\/\/elections.interieur.gouv.fr\/MN2014\/045\/C1045158.html"},"resultat":{"libelle":"R&eacute;sultats re&ccedil;us 1er tour","url":"http:\/\/elections.interieur.gouv.fr\/MN2014\/045\/045158.html"}},"9":{"nom":"Grangermont","Listes":{"libelle":"Candidats (Scrutin majoritaire)","url":"http:\/\/elections.interieur.gouv.fr\/MN2014\/045\/C1045159.html"},"resultat":{"libelle":"R&eacute;sultats re&ccedil;us 1er tour","url":"http:\/\/elections.interieur.gouv.fr\/MN2014\/045\/045159.html"}},"10":{"nom":"Greneville-En-Beauce","Listes":{"libelle":"Candidats (Scrutin majoritaire)","url":"http:\/\/elections.interieur.gouv.fr\/MN2014\/045\/C1045160.html"},"resultat":{"libelle":"R&eacute;sultats re&ccedil;us 1er tour","url":"http:\/\/elections.interieur.gouv.fr\/MN2014\/045\/045160.html"}},"11":{"nom":"Griselles","Listes":{"libelle":"Candidats (Scrutin majoritaire)","url":"http:\/\/elections.interieur.gouv.fr\/MN2014\/045\/C1045161.html"},"resultat":{"libelle":"R&eacute;sultats re&ccedil;us 1er tour","url":"http:\/\/elections.interieur.gouv.fr\/MN2014\/045\/045161.html"}},"12":{"nom":"Guigneville","Listes":{"libelle":"Candidats (Scrutin majoritaire)","url":"http:\/\/elections.interieur.gouv.fr\/MN2014\/045\/C1045162.html"},"resultat":{"libelle":"R&eacute;sultats re&ccedil;us 1er tour","url":"http:\/\/elections.interieur.gouv.fr\/MN2014\/045\/045162.html"}},"13":{"nom":"Guilly","Listes":{"libelle":"Candidats (Scrutin majoritaire)","url":"http:\/\/elections.interieur.gouv.fr\/MN2014\/045\/C1045164.html"},"resultat":{"libelle":"R&eacute;sultats re&ccedil;us 1er tour","url":"http:\/\/elections.interieur.gouv.fr\/MN2014\/045\/045164.html"}},"14":{"nom":"Gy-Les-Nonains","Listes":{"libelle":"Candidats (Scrutin majoritaire)","url":"http:\/\/elections.interieur.gouv.fr\/MN2014\/045\/C1045165.html"},"resultat":{"libelle":"R&eacute;sultats re&ccedil;us 1er tour","url":"http:\/\/elections.interieur.gouv.fr\/MN2014\/045\/045165.html"}}}},"8":{"url":"http:\/\/elections.interieur.gouv.fr\/MN2014\/045\/045H.html","libelle":"H","villes":{"1":{"nom":"Hu&ecirc;tre","Listes":{"libelle":"Candidats (Scrutin majoritaire)","url":"http:\/\/elections.interieur.gouv.fr\/MN2014\/045\/C1045166.html"},"resultat":{"libelle":"R&eacute;sultats re&ccedil;us 1er tour","url":"http:\/\/elections.interieur.gouv.fr\/MN2014\/045\/045166.html"}},"2":{"nom":"Huisseau-Sur-Mauves","Listes":{"libelle":"Listes","url":"http:\/\/elections.interieur.gouv.fr\/MN2014\/045\/C1045167.html"},"resultat":{"libelle":"R&eacute;sultats re&ccedil;us 1er tour","url":"http:\/\/elections.interieur.gouv.fr\/MN2014\/045\/045167.html"}}}},"9":{"url":"http:\/\/elections.interieur.gouv.fr\/MN2014\/045\/045I.html","libelle":"I","villes":{"1":{"nom":"Ingrannes","Listes":{"libelle":"Candidats (Scrutin majoritaire)","url":"http:\/\/elections.interieur.gouv.fr\/MN2014\/045\/C1045168.html"},"resultat":{"libelle":"R&eacute;sultats re&ccedil;us 1er tour","url":"http:\/\/elections.interieur.gouv.fr\/MN2014\/045\/045168.html"}},"2":{"nom":"Ingr&eacute;","Listes":{"libelle":"Listes","url":"http:\/\/elections.interieur.gouv.fr\/MN2014\/045\/C1045169.html"},"resultat":{"libelle":"R&eacute;sultats re&ccedil;us 1er tour","url":"http:\/\/elections.interieur.gouv.fr\/MN2014\/045\/045169.html"}},"3":{"nom":"Intville-La-Gu&eacute;tard","Listes":{"libelle":"Candidats (Scrutin majoritaire)","url":"http:\/\/elections.interieur.gouv.fr\/MN2014\/045\/C1045170.html"},"resultat":{"libelle":"R&eacute;sultats re&ccedil;us 1er tour","url":"http:\/\/elections.interieur.gouv.fr\/MN2014\/045\/045170.html"}},"4":{"nom":"Isdes","Listes":{"libelle":"Candidats (Scrutin majoritaire)","url":"http:\/\/elections.interieur.gouv.fr\/MN2014\/045\/C1045171.html"},"resultat":{"libelle":"R&eacute;sultats re&ccedil;us 1er tour","url":"http:\/\/elections.interieur.gouv.fr\/MN2014\/045\/045171.html"}}}},"10":{"url":"http:\/\/elections.interieur.gouv.fr\/MN2014\/045\/045J.html","libelle":"J","villes":{"1":{"nom":"Jargeau","Listes":{"libelle":"Listes","url":"http:\/\/elections.interieur.gouv.fr\/MN2014\/045\/C1045173.html"},"resultat":{"libelle":"R&eacute;sultats re&ccedil;us 1er tour","url":"http:\/\/elections.interieur.gouv.fr\/MN2014\/045\/045173.html"}},"2":{"nom":"Jouy-En-Pithiverais","Listes":{"libelle":"Candidats (Scrutin majoritaire)","url":"http:\/\/elections.interieur.gouv.fr\/MN2014\/045\/C1045174.html"},"resultat":{"libelle":"R&eacute;sultats re&ccedil;us 1er tour","url":"http:\/\/elections.interieur.gouv.fr\/MN2014\/045\/045174.html"}},"3":{"nom":"Jouy-Le-Potier","Listes":{"libelle":"Listes","url":"http:\/\/elections.interieur.gouv.fr\/MN2014\/045\/C1045175.html"},"resultat":{"libelle":"R&eacute;sultats re&ccedil;us 1er tour","url":"http:\/\/elections.interieur.gouv.fr\/MN2014\/045\/045175.html"}},"4":{"nom":"Juranville","Listes":{"libelle":"Candidats (Scrutin majoritaire)","url":"http:\/\/elections.interieur.gouv.fr\/MN2014\/045\/C1045176.html"},"resultat":{"libelle":"R&eacute;sultats re&ccedil;us 1er tour","url":"http:\/\/elections.interieur.gouv.fr\/MN2014\/045\/045176.html"}}}},"11":{"url":"http:\/\/elections.interieur.gouv.fr\/MN2014\/045\/045L.html","libelle":"L","villes":{"1":{"nom":"La Bussi&egrave;re","Listes":{"libelle":"Candidats (Scrutin majoritaire)","url":"http:\/\/elections.interieur.gouv.fr\/MN2014\/045\/C1045060.html"},"resultat":{"libelle":"R&eacute;sultats re&ccedil;us 1er tour","url":"http:\/\/elections.interieur.gouv.fr\/MN2014\/045\/045060.html"}},"2":{"nom":"La Chapelle-Onzerain","Listes":{"libelle":"Candidats (Scrutin majoritaire)","url":"http:\/\/elections.interieur.gouv.fr\/MN2014\/045\/C1045074.html"},"resultat":{"libelle":"R&eacute;sultats re&ccedil;us 1er tour","url":"http:\/\/elections.interieur.gouv.fr\/MN2014\/045\/045074.html"}},"3":{"nom":"La Chapelle-Saint-Mesmin","Listes":{"libelle":"Listes","url":"http:\/\/elections.interieur.gouv.fr\/MN2014\/045\/C1045075.html"},"resultat":{"libelle":"R&eacute;sultats re&ccedil;us 1er tour","url":"http:\/\/elections.interieur.gouv.fr\/MN2014\/045\/045075.html"}},"4":{"nom":"La Chapelle-Saint-S&eacute;pulcre","Listes":{"libelle":"Candidats (Scrutin majoritaire)","url":"http:\/\/elections.interieur.gouv.fr\/MN2014\/045\/C1045076.html"},"resultat":{"libelle":"R&eacute;sultats re&ccedil;us 1er tour","url":"http:\/\/elections.interieur.gouv.fr\/MN2014\/045\/045076.html"}},"5":{"nom":"La Chapelle-Sur-Aveyron","Listes":{"libelle":"Candidats (Scrutin majoritaire)","url":"http:\/\/elections.interieur.gouv.fr\/MN2014\/045\/C1045077.html"},"resultat":{"libelle":"R&eacute;sultats re&ccedil;us 1er tour","url":"http:\/\/elections.interieur.gouv.fr\/MN2014\/045\/045077.html"}},"6":{"nom":"La Cour-Marigny","Listes":{"libelle":"Candidats (Scrutin majoritaire)","url":"http:\/\/elections.interieur.gouv.fr\/MN2014\/045\/C1045112.html"},"resultat":{"libelle":"R&eacute;sultats re&ccedil;us 1er tour","url":"http:\/\/elections.interieur.gouv.fr\/MN2014\/045\/045112.html"}},"7":{"nom":"La Fert&eacute;-Saint-Aubin","Listes":{"libelle":"Listes","url":"http:\/\/elections.interieur.gouv.fr\/MN2014\/045\/C1045146.html"},"resultat":{"libelle":"R&eacute;sultats re&ccedil;us 1er tour","url":"http:\/\/elections.interieur.gouv.fr\/MN2014\/045\/045146.html"}},"8":{"nom":"La Neuville-Sur-Essonne","Listes":{"libelle":"Candidats (Scrutin majoritaire)","url":"http:\/\/elections.interieur.gouv.fr\/MN2014\/045\/C1045225.html"},"resultat":{"libelle":"R&eacute;sultats re&ccedil;us 1er tour","url":"http:\/\/elections.interieur.gouv.fr\/MN2014\/045\/045225.html"}},"9":{"nom":"La Selle-En-Hermoy","Listes":{"libelle":"Candidats (Scrutin majoritaire)","url":"http:\/\/elections.interieur.gouv.fr\/MN2014\/045\/C1045306.html"},"resultat":{"libelle":"R&eacute;sultats re&ccedil;us 1er tour","url":"http:\/\/elections.interieur.gouv.fr\/MN2014\/045\/045306.html"}},"10":{"nom":"La Selle-Sur-Le-Bied","Listes":{"libelle":"Listes","url":"http:\/\/elections.interieur.gouv.fr\/MN2014\/045\/C1045307.html"},"resultat":{"libelle":"R&eacute;sultats re&ccedil;us 1er tour","url":"http:\/\/elections.interieur.gouv.fr\/MN2014\/045\/045307.html"}},"11":{"nom":"Laas","Listes":{"libelle":"Candidats (Scrutin majoritaire)","url":"http:\/\/elections.interieur.gouv.fr\/MN2014\/045\/C1045177.html"},"resultat":{"libelle":"R&eacute;sultats re&ccedil;us 1er tour","url":"http:\/\/elections.interieur.gouv.fr\/MN2014\/045\/045177.html"}},"12":{"nom":"Labrosse","Listes":{"libelle":"Candidats (Scrutin majoritaire)","url":"http:\/\/elections.interieur.gouv.fr\/MN2014\/045\/C1045057.html"},"resultat":{"libelle":"R&eacute;sultats re&ccedil;us 1er tour","url":"http:\/\/elections.interieur.gouv.fr\/MN2014\/045\/045057.html"}},"13":{"nom":"Ladon","Listes":{"libelle":"Listes","url":"http:\/\/elections.interieur.gouv.fr\/MN2014\/045\/C1045178.html"},"resultat":{"libelle":"R&eacute;sultats re&ccedil;us 1er tour","url":"http:\/\/elections.interieur.gouv.fr\/MN2014\/045\/045178.html"}},"14":{"nom":"Lailly-En-Val","Listes":{"libelle":"Listes","url":"http:\/\/elections.interieur.gouv.fr\/MN2014\/045\/C1045179.html"},"resultat":{"libelle":"R&eacute;sultats re&ccedil;us 1er tour","url":"http:\/\/elections.interieur.gouv.fr\/MN2014\/045\/045179.html"}},"15":{"nom":"Langesse","Listes":{"libelle":"Candidats (Scrutin majoritaire)","url":"http:\/\/elections.interieur.gouv.fr\/MN2014\/045\/C1045180.html"},"resultat":{"libelle":"R&eacute;sultats re&ccedil;us 1er tour","url":"http:\/\/elections.interieur.gouv.fr\/MN2014\/045\/045180.html"}},"16":{"nom":"Le Bardon","Listes":{"libelle":"Listes","url":"http:\/\/elections.interieur.gouv.fr\/MN2014\/045\/C1045020.html"},"resultat":{"libelle":"R&eacute;sultats re&ccedil;us 1er tour","url":"http:\/\/elections.interieur.gouv.fr\/MN2014\/045\/045020.html"}},"17":{"nom":"Le Bignon-Mirabeau","Listes":{"libelle":"Candidats (Scrutin majoritaire)","url":"http:\/\/elections.interieur.gouv.fr\/MN2014\/045\/C1045032.html"},"resultat":{"libelle":"R&eacute;sultats re&ccedil;us 1er tour","url":"http:\/\/elections.interieur.gouv.fr\/MN2014\/045\/045032.html"}},"18":{"nom":"Le Charme","Listes":{"libelle":"Candidats (Scrutin majoritaire)","url":"http:\/\/elections.interieur.gouv.fr\/MN2014\/045\/C1045079.html"},"resultat":{"libelle":"R&eacute;sultats re&ccedil;us 1er tour","url":"http:\/\/elections.interieur.gouv.fr\/MN2014\/045\/045079.html"}},"19":{"nom":"Le Moulinet-Sur-Solin","Listes":{"libelle":"Candidats (Scrutin majoritaire)","url":"http:\/\/elections.interieur.gouv.fr\/MN2014\/045\/C1045218.html"},"resultat":{"libelle":"R&eacute;sultats re&ccedil;us 1er tour","url":"http:\/\/elections.interieur.gouv.fr\/MN2014\/045\/045218.html"}},"20":{"nom":"L&eacute;ouville","Listes":{"libelle":"Candidats (Scrutin majoritaire)","url":"http:\/\/elections.interieur.gouv.fr\/MN2014\/045\/C1045181.html"},"resultat":{"libelle":"R&eacute;sultats re&ccedil;us 1er tour","url":"http:\/\/elections.interieur.gouv.fr\/MN2014\/045\/045181.html"}},"21":{"nom":"Les Bordes","Listes":{"libelle":"Listes","url":"http:\/\/elections.interieur.gouv.fr\/MN2014\/045\/C1045042.html"},"resultat":{"libelle":"R&eacute;sultats re&ccedil;us 1er tour","url":"http:\/\/elections.interieur.gouv.fr\/MN2014\/045\/045042.html"}},"22":{"nom":"Les Choux","Listes":{"libelle":"Candidats (Scrutin majoritaire)","url":"http:\/\/elections.interieur.gouv.fr\/MN2014\/045\/C1045096.html"},"resultat":{"libelle":"R&eacute;sultats re&ccedil;us 1er tour","url":"http:\/\/elections.interieur.gouv.fr\/MN2014\/045\/045096.html"}},"23":{"nom":"Ligny-Le-Ribault","Listes":{"libelle":"Listes","url":"http:\/\/elections.interieur.gouv.fr\/MN2014\/045\/C1045182.html"},"resultat":{"libelle":"R&eacute;sultats re&ccedil;us 1er tour","url":"http:\/\/elections.interieur.gouv.fr\/MN2014\/045\/045182.html"}},"24":{"nom":"Lion-En-Beauce","Listes":{"libelle":"Candidats (Scrutin majoritaire)","url":"http:\/\/elections.interieur.gouv.fr\/MN2014\/045\/C1045183.html"},"resultat":{"libelle":"\n\t\t\t\tAucun r&eacute;sultat re&ccedil;u\n\t\t\t","url":"http:\/\/elections.interieur.gouv.fr\/MN2014\/045\/"}},"25":{"nom":"Lion-En-Sullias","Listes":{"libelle":"Candidats (Scrutin majoritaire)","url":"http:\/\/elections.interieur.gouv.fr\/MN2014\/045\/C1045184.html"},"resultat":{"libelle":"R&eacute;sultats re&ccedil;us 1er tour","url":"http:\/\/elections.interieur.gouv.fr\/MN2014\/045\/045184.html"}},"26":{"nom":"Lombreuil","Listes":{"libelle":"Candidats (Scrutin majoritaire)","url":"http:\/\/elections.interieur.gouv.fr\/MN2014\/045\/C1045185.html"},"resultat":{"libelle":"R&eacute;sultats re&ccedil;us 1er tour","url":"http:\/\/elections.interieur.gouv.fr\/MN2014\/045\/045185.html"}},"27":{"nom":"Lorcy","Listes":{"libelle":"Candidats (Scrutin majoritaire)","url":"http:\/\/elections.interieur.gouv.fr\/MN2014\/045\/C1045186.html"},"resultat":{"libelle":"R&eacute;sultats re&ccedil;us 1er tour","url":"http:\/\/elections.interieur.gouv.fr\/MN2014\/045\/045186.html"}},"28":{"nom":"Lorris","Listes":{"libelle":"Listes","url":"http:\/\/elections.interieur.gouv.fr\/MN2014\/045\/C1045187.html"},"resultat":{"libelle":"R&eacute;sultats re&ccedil;us 1er tour","url":"http:\/\/elections.interieur.gouv.fr\/MN2014\/045\/045187.html"}},"29":{"nom":"Loury","Listes":{"libelle":"Listes","url":"http:\/\/elections.interieur.gouv.fr\/MN2014\/045\/C1045188.html"},"resultat":{"libelle":"R&eacute;sultats re&ccedil;us 1er tour","url":"http:\/\/elections.interieur.gouv.fr\/MN2014\/045\/045188.html"}},"30":{"nom":"Louzouer","Listes":{"libelle":"Candidats (Scrutin majoritaire)","url":"http:\/\/elections.interieur.gouv.fr\/MN2014\/045\/C1045189.html"},"resultat":{"libelle":"R&eacute;sultats re&ccedil;us 1er tour","url":"http:\/\/elections.interieur.gouv.fr\/MN2014\/045\/045189.html"}}}},"12":{"url":"http:\/\/elections.interieur.gouv.fr\/MN2014\/045\/045M.html","libelle":"M","villes":{"1":{"nom":"Mainvilliers","Listes":{"libelle":"Candidats (Scrutin majoritaire)","url":"http:\/\/elections.interieur.gouv.fr\/MN2014\/045\/C1045190.html"},"resultat":{"libelle":"R&eacute;sultats re&ccedil;us 1er tour","url":"http:\/\/elections.interieur.gouv.fr\/MN2014\/045\/045190.html"}},"2":{"nom":"Malesherbes","Listes":{"libelle":"Listes","url":"http:\/\/elections.interieur.gouv.fr\/MN2014\/045\/C1045191.html"},"resultat":{"libelle":"R&eacute;sultats re&ccedil;us 1er tour","url":"http:\/\/elections.interieur.gouv.fr\/MN2014\/045\/045191.html"}},"3":{"nom":"Manchecourt","Listes":{"libelle":"Candidats (Scrutin majoritaire)","url":"http:\/\/elections.interieur.gouv.fr\/MN2014\/045\/C1045192.html"},"resultat":{"libelle":"R&eacute;sultats re&ccedil;us 1er tour","url":"http:\/\/elections.interieur.gouv.fr\/MN2014\/045\/045192.html"}},"4":{"nom":"Marcilly-En-Villette","Listes":{"libelle":"Listes","url":"http:\/\/elections.interieur.gouv.fr\/MN2014\/045\/C1045193.html"},"resultat":{"libelle":"R&eacute;sultats re&ccedil;us 1er tour","url":"http:\/\/elections.interieur.gouv.fr\/MN2014\/045\/045193.html"}},"5":{"nom":"Mardi&eacute;","Listes":{"libelle":"Listes","url":"http:\/\/elections.interieur.gouv.fr\/MN2014\/045\/C1045194.html"},"resultat":{"libelle":"R&eacute;sultats re&ccedil;us 1er tour","url":"http:\/\/elections.interieur.gouv.fr\/MN2014\/045\/045194.html"}},"6":{"nom":"Mareau-Aux-Bois","Listes":{"libelle":"Candidats (Scrutin majoritaire)","url":"http:\/\/elections.interieur.gouv.fr\/MN2014\/045\/C1045195.html"},"resultat":{"libelle":"R&eacute;sultats re&ccedil;us 1er tour","url":"http:\/\/elections.interieur.gouv.fr\/MN2014\/045\/045195.html"}},"7":{"nom":"Mareau-Aux-Pr&eacute;s","Listes":{"libelle":"Listes","url":"http:\/\/elections.interieur.gouv.fr\/MN2014\/045\/C1045196.html"},"resultat":{"libelle":"R&eacute;sultats re&ccedil;us 1er tour","url":"http:\/\/elections.interieur.gouv.fr\/MN2014\/045\/045196.html"}},"8":{"nom":"Marigny-Les-Usages","Listes":{"libelle":"Listes","url":"http:\/\/elections.interieur.gouv.fr\/MN2014\/045\/C1045197.html"},"resultat":{"libelle":"R&eacute;sultats re&ccedil;us 1er tour","url":"http:\/\/elections.interieur.gouv.fr\/MN2014\/045\/045197.html"}},"9":{"nom":"Marsainvilliers","Listes":{"libelle":"Candidats (Scrutin majoritaire)","url":"http:\/\/elections.interieur.gouv.fr\/MN2014\/045\/C1045198.html"},"resultat":{"libelle":"R&eacute;sultats re&ccedil;us 1er tour","url":"http:\/\/elections.interieur.gouv.fr\/MN2014\/045\/045198.html"}},"10":{"nom":"Melleroy","Listes":{"libelle":"Candidats (Scrutin majoritaire)","url":"http:\/\/elections.interieur.gouv.fr\/MN2014\/045\/C1045199.html"},"resultat":{"libelle":"R&eacute;sultats re&ccedil;us 1er tour","url":"http:\/\/elections.interieur.gouv.fr\/MN2014\/045\/045199.html"}},"11":{"nom":"M&eacute;nestreau-En-Villette","Listes":{"libelle":"Listes","url":"http:\/\/elections.interieur.gouv.fr\/MN2014\/045\/C1045200.html"},"resultat":{"libelle":"R&eacute;sultats re&ccedil;us 1er tour","url":"http:\/\/elections.interieur.gouv.fr\/MN2014\/045\/045200.html"}},"12":{"nom":"M&eacute;rinville","Listes":{"libelle":"Candidats (Scrutin majoritaire)","url":"http:\/\/elections.interieur.gouv.fr\/MN2014\/045\/C1045201.html"},"resultat":{"libelle":"R&eacute;sultats re&ccedil;us 1er tour","url":"http:\/\/elections.interieur.gouv.fr\/MN2014\/045\/045201.html"}},"13":{"nom":"Messas","Listes":{"libelle":"Candidats (Scrutin majoritaire)","url":"http:\/\/elections.interieur.gouv.fr\/MN2014\/045\/C1045202.html"},"resultat":{"libelle":"R&eacute;sultats re&ccedil;us 1er tour","url":"http:\/\/elections.interieur.gouv.fr\/MN2014\/045\/045202.html"}},"14":{"nom":"Meung-Sur-Loire","Listes":{"libelle":"Listes","url":"http:\/\/elections.interieur.gouv.fr\/MN2014\/045\/C1045203.html"},"resultat":{"libelle":"R&eacute;sultats re&ccedil;us 1er tour","url":"http:\/\/elections.interieur.gouv.fr\/MN2014\/045\/045203.html"}},"15":{"nom":"M&eacute;zi&egrave;res-En-G&acirc;tinais","Listes":{"libelle":"Candidats (Scrutin majoritaire)","url":"http:\/\/elections.interieur.gouv.fr\/MN2014\/045\/C1045205.html"},"resultat":{"libelle":"R&eacute;sultats re&ccedil;us 1er tour","url":"http:\/\/elections.interieur.gouv.fr\/MN2014\/045\/045205.html"}},"16":{"nom":"M&eacute;zi&egrave;res-Lez-Cl&eacute;ry","Listes":{"libelle":"Candidats (Scrutin majoritaire)","url":"http:\/\/elections.interieur.gouv.fr\/MN2014\/045\/C1045204.html"},"resultat":{"libelle":"R&eacute;sultats re&ccedil;us 1er tour","url":"http:\/\/elections.interieur.gouv.fr\/MN2014\/045\/045204.html"}},"17":{"nom":"Mign&egrave;res","Listes":{"libelle":"Candidats (Scrutin majoritaire)","url":"http:\/\/elections.interieur.gouv.fr\/MN2014\/045\/C1045206.html"},"resultat":{"libelle":"R&eacute;sultats re&ccedil;us 1er tour","url":"http:\/\/elections.interieur.gouv.fr\/MN2014\/045\/045206.html"}},"18":{"nom":"Mignerette","Listes":{"libelle":"Candidats (Scrutin majoritaire)","url":"http:\/\/elections.interieur.gouv.fr\/MN2014\/045\/C1045207.html"},"resultat":{"libelle":"R&eacute;sultats re&ccedil;us 1er tour","url":"http:\/\/elections.interieur.gouv.fr\/MN2014\/045\/045207.html"}},"19":{"nom":"Montargis","Listes":{"libelle":"Listes","url":"http:\/\/elections.interieur.gouv.fr\/MN2014\/045\/C1045208.html"},"resultat":{"libelle":"R&eacute;sultats re&ccedil;us 1er tour","url":"http:\/\/elections.interieur.gouv.fr\/MN2014\/045\/045208.html"}},"20":{"nom":"Montbarrois","Listes":{"libelle":"Candidats (Scrutin majoritaire)","url":"http:\/\/elections.interieur.gouv.fr\/MN2014\/045\/C1045209.html"},"resultat":{"libelle":"R&eacute;sultats re&ccedil;us 1er tour","url":"http:\/\/elections.interieur.gouv.fr\/MN2014\/045\/045209.html"}},"21":{"nom":"Montbouy","Listes":{"libelle":"Candidats (Scrutin majoritaire)","url":"http:\/\/elections.interieur.gouv.fr\/MN2014\/045\/C1045210.html"},"resultat":{"libelle":"R&eacute;sultats re&ccedil;us 1er tour","url":"http:\/\/elections.interieur.gouv.fr\/MN2014\/045\/045210.html"}},"22":{"nom":"Montcorbon","Listes":{"libelle":"Candidats (Scrutin majoritaire)","url":"http:\/\/elections.interieur.gouv.fr\/MN2014\/045\/C1045211.html"},"resultat":{"libelle":"R&eacute;sultats re&ccedil;us 1er tour","url":"http:\/\/elections.interieur.gouv.fr\/MN2014\/045\/045211.html"}},"23":{"nom":"Montcresson","Listes":{"libelle":"Listes","url":"http:\/\/elections.interieur.gouv.fr\/MN2014\/045\/C1045212.html"},"resultat":{"libelle":"R&eacute;sultats re&ccedil;us 1er tour","url":"http:\/\/elections.interieur.gouv.fr\/MN2014\/045\/045212.html"}},"24":{"nom":"Montereau","Listes":{"libelle":"Candidats (Scrutin majoritaire)","url":"http:\/\/elections.interieur.gouv.fr\/MN2014\/045\/C1045213.html"},"resultat":{"libelle":"R&eacute;sultats re&ccedil;us 1er tour","url":"http:\/\/elections.interieur.gouv.fr\/MN2014\/045\/045213.html"}},"25":{"nom":"Montigny","Listes":{"libelle":"Candidats (Scrutin majoritaire)","url":"http:\/\/elections.interieur.gouv.fr\/MN2014\/045\/C1045214.html"},"resultat":{"libelle":"R&eacute;sultats re&ccedil;us 1er tour","url":"http:\/\/elections.interieur.gouv.fr\/MN2014\/045\/045214.html"}},"26":{"nom":"Montliard","Listes":{"libelle":"Candidats (Scrutin majoritaire)","url":"http:\/\/elections.interieur.gouv.fr\/MN2014\/045\/C1045215.html"},"resultat":{"libelle":"R&eacute;sultats re&ccedil;us 1er tour","url":"http:\/\/elections.interieur.gouv.fr\/MN2014\/045\/045215.html"}},"27":{"nom":"Mormant-Sur-Vernisson","Listes":{"libelle":"Candidats (Scrutin majoritaire)","url":"http:\/\/elections.interieur.gouv.fr\/MN2014\/045\/C1045216.html"},"resultat":{"libelle":"R&eacute;sultats re&ccedil;us 1er tour","url":"http:\/\/elections.interieur.gouv.fr\/MN2014\/045\/045216.html"}},"28":{"nom":"Morville-En-Beauce","Listes":{"libelle":"Candidats (Scrutin majoritaire)","url":"http:\/\/elections.interieur.gouv.fr\/MN2014\/045\/C1045217.html"},"resultat":{"libelle":"R&eacute;sultats re&ccedil;us 1er tour","url":"http:\/\/elections.interieur.gouv.fr\/MN2014\/045\/045217.html"}},"29":{"nom":"Moulon","Listes":{"libelle":"Candidats (Scrutin majoritaire)","url":"http:\/\/elections.interieur.gouv.fr\/MN2014\/045\/C1045219.html"},"resultat":{"libelle":"R&eacute;sultats re&ccedil;us 1er tour","url":"http:\/\/elections.interieur.gouv.fr\/MN2014\/045\/045219.html"}}}},"13":{"url":"http:\/\/elections.interieur.gouv.fr\/MN2014\/045\/045N.html","libelle":"N","villes":{"1":{"nom":"Nancray-Sur-Rimarde","Listes":{"libelle":"Candidats (Scrutin majoritaire)","url":"http:\/\/elections.interieur.gouv.fr\/MN2014\/045\/C1045220.html"},"resultat":{"libelle":"R&eacute;sultats re&ccedil;us 1er tour","url":"http:\/\/elections.interieur.gouv.fr\/MN2014\/045\/045220.html"}},"2":{"nom":"Nangeville","Listes":{"libelle":"Candidats (Scrutin majoritaire)","url":"http:\/\/elections.interieur.gouv.fr\/MN2014\/045\/C1045221.html"},"resultat":{"libelle":"R&eacute;sultats re&ccedil;us 1er tour","url":"http:\/\/elections.interieur.gouv.fr\/MN2014\/045\/045221.html"}},"3":{"nom":"Nargis","Listes":{"libelle":"Listes","url":"http:\/\/elections.interieur.gouv.fr\/MN2014\/045\/C1045222.html"},"resultat":{"libelle":"R&eacute;sultats re&ccedil;us 1er tour","url":"http:\/\/elections.interieur.gouv.fr\/MN2014\/045\/045222.html"}},"4":{"nom":"Nesploy","Listes":{"libelle":"Candidats (Scrutin majoritaire)","url":"http:\/\/elections.interieur.gouv.fr\/MN2014\/045\/C1045223.html"},"resultat":{"libelle":"R&eacute;sultats re&ccedil;us 1er tour","url":"http:\/\/elections.interieur.gouv.fr\/MN2014\/045\/045223.html"}},"5":{"nom":"Neuville-Aux-Bois","Listes":{"libelle":"Listes","url":"http:\/\/elections.interieur.gouv.fr\/MN2014\/045\/C1045224.html"},"resultat":{"libelle":"R&eacute;sultats re&ccedil;us 1er tour","url":"http:\/\/elections.interieur.gouv.fr\/MN2014\/045\/045224.html"}},"6":{"nom":"Neuvy-En-Sullias","Listes":{"libelle":"Listes","url":"http:\/\/elections.interieur.gouv.fr\/MN2014\/045\/C1045226.html"},"resultat":{"libelle":"R&eacute;sultats re&ccedil;us 1er tour","url":"http:\/\/elections.interieur.gouv.fr\/MN2014\/045\/045226.html"}},"7":{"nom":"Nevoy","Listes":{"libelle":"Listes","url":"http:\/\/elections.interieur.gouv.fr\/MN2014\/045\/C1045227.html"},"resultat":{"libelle":"R&eacute;sultats re&ccedil;us 1er tour","url":"http:\/\/elections.interieur.gouv.fr\/MN2014\/045\/045227.html"}},"8":{"nom":"Nibelle","Listes":{"libelle":"Listes","url":"http:\/\/elections.interieur.gouv.fr\/MN2014\/045\/C1045228.html"},"resultat":{"libelle":"R&eacute;sultats re&ccedil;us 1er tour","url":"http:\/\/elections.interieur.gouv.fr\/MN2014\/045\/045228.html"}},"9":{"nom":"Nogent-Sur-Vernisson","Listes":{"libelle":"Listes","url":"http:\/\/elections.interieur.gouv.fr\/MN2014\/045\/C1045229.html"},"resultat":{"libelle":"R&eacute;sultats re&ccedil;us 1er tour","url":"http:\/\/elections.interieur.gouv.fr\/MN2014\/045\/045229.html"}},"10":{"nom":"Noyers","Listes":{"libelle":"Candidats (Scrutin majoritaire)","url":"http:\/\/elections.interieur.gouv.fr\/MN2014\/045\/C1045230.html"},"resultat":{"libelle":"R&eacute;sultats re&ccedil;us 1er tour","url":"http:\/\/elections.interieur.gouv.fr\/MN2014\/045\/045230.html"}}}},"14":{"url":"http:\/\/elections.interieur.gouv.fr\/MN2014\/045\/045O.html","libelle":"O","villes":{"1":{"nom":"Oison","Listes":{"libelle":"Candidats (Scrutin majoritaire)","url":"http:\/\/elections.interieur.gouv.fr\/MN2014\/045\/C1045231.html"},"resultat":{"libelle":"R&eacute;sultats re&ccedil;us 1er tour","url":"http:\/\/elections.interieur.gouv.fr\/MN2014\/045\/045231.html"}},"2":{"nom":"Olivet","Listes":{"libelle":"Listes","url":"http:\/\/elections.interieur.gouv.fr\/MN2014\/045\/C1045232.html"},"resultat":{"libelle":"R&eacute;sultats re&ccedil;us 1er tour","url":"http:\/\/elections.interieur.gouv.fr\/MN2014\/045\/045232.html"}},"3":{"nom":"Ondreville-Sur-Essonne","Listes":{"libelle":"Candidats (Scrutin majoritaire)","url":"http:\/\/elections.interieur.gouv.fr\/MN2014\/045\/C1045233.html"},"resultat":{"libelle":"R&eacute;sultats re&ccedil;us 1er tour","url":"http:\/\/elections.interieur.gouv.fr\/MN2014\/045\/045233.html"}},"4":{"nom":"Orl&eacute;ans","Listes":{"libelle":"Listes","url":"http:\/\/elections.interieur.gouv.fr\/MN2014\/045\/C1045234.html"},"resultat":{"libelle":"R&eacute;sultats re&ccedil;us 1er tour","url":"http:\/\/elections.interieur.gouv.fr\/MN2014\/045\/045234.html"}},"5":{"nom":"Ormes","Listes":{"libelle":"Listes","url":"http:\/\/elections.interieur.gouv.fr\/MN2014\/045\/C1045235.html"},"resultat":{"libelle":"R&eacute;sultats re&ccedil;us 1er tour","url":"http:\/\/elections.interieur.gouv.fr\/MN2014\/045\/045235.html"}},"6":{"nom":"Orveau-Bellesauve","Listes":{"libelle":"Candidats (Scrutin majoritaire)","url":"http:\/\/elections.interieur.gouv.fr\/MN2014\/045\/C1045236.html"},"resultat":{"libelle":"R&eacute;sultats re&ccedil;us 1er tour","url":"http:\/\/elections.interieur.gouv.fr\/MN2014\/045\/045236.html"}},"7":{"nom":"Orville","Listes":{"libelle":"Candidats (Scrutin majoritaire)","url":"http:\/\/elections.interieur.gouv.fr\/MN2014\/045\/C1045237.html"},"resultat":{"libelle":"R&eacute;sultats re&ccedil;us 1er tour","url":"http:\/\/elections.interieur.gouv.fr\/MN2014\/045\/045237.html"}},"8":{"nom":"Ousson-Sur-Loire","Listes":{"libelle":"Candidats (Scrutin majoritaire)","url":"http:\/\/elections.interieur.gouv.fr\/MN2014\/045\/C1045238.html"},"resultat":{"libelle":"R&eacute;sultats re&ccedil;us 1er tour","url":"http:\/\/elections.interieur.gouv.fr\/MN2014\/045\/045238.html"}},"9":{"nom":"Oussoy-En-G&acirc;tinais","Listes":{"libelle":"Candidats (Scrutin majoritaire)","url":"http:\/\/elections.interieur.gouv.fr\/MN2014\/045\/C1045239.html"},"resultat":{"libelle":"R&eacute;sultats re&ccedil;us 1er tour","url":"http:\/\/elections.interieur.gouv.fr\/MN2014\/045\/045239.html"}},"10":{"nom":"Outarville","Listes":{"libelle":"Listes","url":"http:\/\/elections.interieur.gouv.fr\/MN2014\/045\/C1045240.html"},"resultat":{"libelle":"R&eacute;sultats re&ccedil;us 1er tour","url":"http:\/\/elections.interieur.gouv.fr\/MN2014\/045\/045240.html"}},"11":{"nom":"Ouvrouer-Les-Champs","Listes":{"libelle":"Candidats (Scrutin majoritaire)","url":"http:\/\/elections.interieur.gouv.fr\/MN2014\/045\/C1045241.html"},"resultat":{"libelle":"R&eacute;sultats re&ccedil;us 1er tour","url":"http:\/\/elections.interieur.gouv.fr\/MN2014\/045\/045241.html"}},"12":{"nom":"Ouzouer-Des-Champs","Listes":{"libelle":"Candidats (Scrutin majoritaire)","url":"http:\/\/elections.interieur.gouv.fr\/MN2014\/045\/C1045242.html"},"resultat":{"libelle":"R&eacute;sultats re&ccedil;us 1er tour","url":"http:\/\/elections.interieur.gouv.fr\/MN2014\/045\/045242.html"}},"13":{"nom":"Ouzouer-Sous-Bellegarde","Listes":{"libelle":"Candidats (Scrutin majoritaire)","url":"http:\/\/elections.interieur.gouv.fr\/MN2014\/045\/C1045243.html"},"resultat":{"libelle":"R&eacute;sultats re&ccedil;us 1er tour","url":"http:\/\/elections.interieur.gouv.fr\/MN2014\/045\/045243.html"}},"14":{"nom":"Ouzouer-Sur-Loire","Listes":{"libelle":"Listes","url":"http:\/\/elections.interieur.gouv.fr\/MN2014\/045\/C1045244.html"},"resultat":{"libelle":"R&eacute;sultats re&ccedil;us 1er tour","url":"http:\/\/elections.interieur.gouv.fr\/MN2014\/045\/045244.html"}},"15":{"nom":"Ouzouer-Sur-Tr&eacute;z&eacute;e","Listes":{"libelle":"Listes","url":"http:\/\/elections.interieur.gouv.fr\/MN2014\/045\/C1045245.html"},"resultat":{"libelle":"R&eacute;sultats re&ccedil;us 1er tour","url":"http:\/\/elections.interieur.gouv.fr\/MN2014\/045\/045245.html"}}}},"15":{"url":"http:\/\/elections.interieur.gouv.fr\/MN2014\/045\/045P.html","libelle":"P","villes":{"1":{"nom":"Panneci&egrave;res","Listes":{"libelle":"Candidats (Scrutin majoritaire)","url":"http:\/\/elections.interieur.gouv.fr\/MN2014\/045\/C1045246.html"},"resultat":{"libelle":"R&eacute;sultats re&ccedil;us 1er tour","url":"http:\/\/elections.interieur.gouv.fr\/MN2014\/045\/045246.html"}},"2":{"nom":"Pannes","Listes":{"libelle":"Listes","url":"http:\/\/elections.interieur.gouv.fr\/MN2014\/045\/C1045247.html"},"resultat":{"libelle":"R&eacute;sultats re&ccedil;us 1er tour","url":"http:\/\/elections.interieur.gouv.fr\/MN2014\/045\/045247.html"}},"3":{"nom":"Patay","Listes":{"libelle":"Listes","url":"http:\/\/elections.interieur.gouv.fr\/MN2014\/045\/C1045248.html"},"resultat":{"libelle":"R&eacute;sultats re&ccedil;us 1er tour","url":"http:\/\/elections.interieur.gouv.fr\/MN2014\/045\/045248.html"}},"4":{"nom":"Paucourt","Listes":{"libelle":"Candidats (Scrutin majoritaire)","url":"http:\/\/elections.interieur.gouv.fr\/MN2014\/045\/C1045249.html"},"resultat":{"libelle":"R&eacute;sultats re&ccedil;us 1er tour","url":"http:\/\/elections.interieur.gouv.fr\/MN2014\/045\/045249.html"}},"5":{"nom":"Pers-En-G&acirc;tinais","Listes":{"libelle":"Candidats (Scrutin majoritaire)","url":"http:\/\/elections.interieur.gouv.fr\/MN2014\/045\/C1045250.html"},"resultat":{"libelle":"R&eacute;sultats re&ccedil;us 1er tour","url":"http:\/\/elections.interieur.gouv.fr\/MN2014\/045\/045250.html"}},"6":{"nom":"Pierrefitte-&Egrave;s-Bois","Listes":{"libelle":"Candidats (Scrutin majoritaire)","url":"http:\/\/elections.interieur.gouv.fr\/MN2014\/045\/C1045251.html"},"resultat":{"libelle":"R&eacute;sultats re&ccedil;us 1er tour","url":"http:\/\/elections.interieur.gouv.fr\/MN2014\/045\/045251.html"}},"7":{"nom":"Pithiviers","Listes":{"libelle":"Listes","url":"http:\/\/elections.interieur.gouv.fr\/MN2014\/045\/C1045252.html"},"resultat":{"libelle":"R&eacute;sultats re&ccedil;us 1er tour","url":"http:\/\/elections.interieur.gouv.fr\/MN2014\/045\/045252.html"}},"8":{"nom":"Pithiviers-Le-Vieil","Listes":{"libelle":"Listes","url":"http:\/\/elections.interieur.gouv.fr\/MN2014\/045\/C1045253.html"},"resultat":{"libelle":"R&eacute;sultats re&ccedil;us 1er tour","url":"http:\/\/elections.interieur.gouv.fr\/MN2014\/045\/045253.html"}},"9":{"nom":"Poilly-Lez-Gien","Listes":{"libelle":"Listes","url":"http:\/\/elections.interieur.gouv.fr\/MN2014\/045\/C1045254.html"},"resultat":{"libelle":"R&eacute;sultats re&ccedil;us 1er tour","url":"http:\/\/elections.interieur.gouv.fr\/MN2014\/045\/045254.html"}},"10":{"nom":"Pr&eacute;fontaines","Listes":{"libelle":"Candidats (Scrutin majoritaire)","url":"http:\/\/elections.interieur.gouv.fr\/MN2014\/045\/C1045255.html"},"resultat":{"libelle":"R&eacute;sultats re&ccedil;us 1er tour","url":"http:\/\/elections.interieur.gouv.fr\/MN2014\/045\/045255.html"}},"11":{"nom":"Presnoy","Listes":{"libelle":"Candidats (Scrutin majoritaire)","url":"http:\/\/elections.interieur.gouv.fr\/MN2014\/045\/C1045256.html"},"resultat":{"libelle":"R&eacute;sultats re&ccedil;us 1er tour","url":"http:\/\/elections.interieur.gouv.fr\/MN2014\/045\/045256.html"}},"12":{"nom":"Pressigny-Les-Pins","Listes":{"libelle":"Candidats (Scrutin majoritaire)","url":"http:\/\/elections.interieur.gouv.fr\/MN2014\/045\/C1045257.html"},"resultat":{"libelle":"R&eacute;sultats re&ccedil;us 1er tour","url":"http:\/\/elections.interieur.gouv.fr\/MN2014\/045\/045257.html"}},"13":{"nom":"Puiseaux","Listes":{"libelle":"Listes","url":"http:\/\/elections.interieur.gouv.fr\/MN2014\/045\/C1045258.html"},"resultat":{"libelle":"R&eacute;sultats re&ccedil;us 1er tour","url":"http:\/\/elections.interieur.gouv.fr\/MN2014\/045\/045258.html"}}}},"16":{"url":"http:\/\/elections.interieur.gouv.fr\/MN2014\/045\/045Q.html","libelle":"Q","villes":{"1":{"nom":"Quiers-Sur-B&eacute;zonde","Listes":{"libelle":"Listes","url":"http:\/\/elections.interieur.gouv.fr\/MN2014\/045\/C1045259.html"},"resultat":{"libelle":"R&eacute;sultats re&ccedil;us 1er tour","url":"http:\/\/elections.interieur.gouv.fr\/MN2014\/045\/045259.html"}}}},"17":{"url":"http:\/\/elections.interieur.gouv.fr\/MN2014\/045\/045R.html","libelle":"R","villes":{"1":{"nom":"Ramoulu","Listes":{"libelle":"Candidats (Scrutin majoritaire)","url":"http:\/\/elections.interieur.gouv.fr\/MN2014\/045\/C1045260.html"},"resultat":{"libelle":"R&eacute;sultats re&ccedil;us 1er tour","url":"http:\/\/elections.interieur.gouv.fr\/MN2014\/045\/045260.html"}},"2":{"nom":"Rebr&eacute;chien","Listes":{"libelle":"Listes","url":"http:\/\/elections.interieur.gouv.fr\/MN2014\/045\/C1045261.html"},"resultat":{"libelle":"R&eacute;sultats re&ccedil;us 1er tour","url":"http:\/\/elections.interieur.gouv.fr\/MN2014\/045\/045261.html"}},"3":{"nom":"Rosoy-Le-Vieil","Listes":{"libelle":"Candidats (Scrutin majoritaire)","url":"http:\/\/elections.interieur.gouv.fr\/MN2014\/045\/C1045265.html"},"resultat":{"libelle":"R&eacute;sultats re&ccedil;us 1er tour","url":"http:\/\/elections.interieur.gouv.fr\/MN2014\/045\/045265.html"}},"4":{"nom":"Rouvray-Sainte-Croix","Listes":{"libelle":"Candidats (Scrutin majoritaire)","url":"http:\/\/elections.interieur.gouv.fr\/MN2014\/045\/C1045262.html"},"resultat":{"libelle":"R&eacute;sultats re&ccedil;us 1er tour","url":"http:\/\/elections.interieur.gouv.fr\/MN2014\/045\/045262.html"}},"5":{"nom":"Rouvres-Saint-Jean","Listes":{"libelle":"Candidats (Scrutin majoritaire)","url":"http:\/\/elections.interieur.gouv.fr\/MN2014\/045\/C1045263.html"},"resultat":{"libelle":"R&eacute;sultats re&ccedil;us 1er tour","url":"http:\/\/elections.interieur.gouv.fr\/MN2014\/045\/045263.html"}},"6":{"nom":"Rozi&egrave;res-En-Beauce","Listes":{"libelle":"Candidats (Scrutin majoritaire)","url":"http:\/\/elections.interieur.gouv.fr\/MN2014\/045\/C1045264.html"},"resultat":{"libelle":"R&eacute;sultats re&ccedil;us 1er tour","url":"http:\/\/elections.interieur.gouv.fr\/MN2014\/045\/045264.html"}},"7":{"nom":"Ruan","Listes":{"libelle":"Candidats (Scrutin majoritaire)","url":"http:\/\/elections.interieur.gouv.fr\/MN2014\/045\/C1045266.html"},"resultat":{"libelle":"R&eacute;sultats re&ccedil;us 1er tour","url":"http:\/\/elections.interieur.gouv.fr\/MN2014\/045\/045266.html"}}}},"18":{"url":"http:\/\/elections.interieur.gouv.fr\/MN2014\/045\/045S.html","libelle":"S","villes":{"1":{"nom":"Saint-Aignan-Des-Gu&eacute;s","Listes":{"libelle":"Candidats (Scrutin majoritaire)","url":"http:\/\/elections.interieur.gouv.fr\/MN2014\/045\/C1045267.html"},"resultat":{"libelle":"R&eacute;sultats re&ccedil;us 1er tour","url":"http:\/\/elections.interieur.gouv.fr\/MN2014\/045\/045267.html"}},"2":{"nom":"Saint-Aignan-Le-Jaillard","Listes":{"libelle":"Candidats (Scrutin majoritaire)","url":"http:\/\/elections.interieur.gouv.fr\/MN2014\/045\/C1045268.html"},"resultat":{"libelle":"R&eacute;sultats re&ccedil;us 1er tour","url":"http:\/\/elections.interieur.gouv.fr\/MN2014\/045\/045268.html"}},"3":{"nom":"Saint-Ay","Listes":{"libelle":"Listes","url":"http:\/\/elections.interieur.gouv.fr\/MN2014\/045\/C1045269.html"},"resultat":{"libelle":"R&eacute;sultats re&ccedil;us 1er tour","url":"http:\/\/elections.interieur.gouv.fr\/MN2014\/045\/045269.html"}},"4":{"nom":"Saint-Beno&icirc;t-Sur-Loire","Listes":{"libelle":"Listes","url":"http:\/\/elections.interieur.gouv.fr\/MN2014\/045\/C1045270.html"},"resultat":{"libelle":"R&eacute;sultats re&ccedil;us 1er tour","url":"http:\/\/elections.interieur.gouv.fr\/MN2014\/045\/045270.html"}},"5":{"nom":"Saint-Brisson-Sur-Loire","Listes":{"libelle":"Listes","url":"http:\/\/elections.interieur.gouv.fr\/MN2014\/045\/C1045271.html"},"resultat":{"libelle":"R&eacute;sultats re&ccedil;us 1er tour","url":"http:\/\/elections.interieur.gouv.fr\/MN2014\/045\/045271.html"}},"6":{"nom":"Saint-Cyr-En-Val","Listes":{"libelle":"Listes","url":"http:\/\/elections.interieur.gouv.fr\/MN2014\/045\/C1045272.html"},"resultat":{"libelle":"R&eacute;sultats re&ccedil;us 1er tour","url":"http:\/\/elections.interieur.gouv.fr\/MN2014\/045\/045272.html"}},"7":{"nom":"Saint-Denis-De-L'H&ocirc;tel","Listes":{"libelle":"Listes","url":"http:\/\/elections.interieur.gouv.fr\/MN2014\/045\/C1045273.html"},"resultat":{"libelle":"R&eacute;sultats re&ccedil;us 1er tour","url":"http:\/\/elections.interieur.gouv.fr\/MN2014\/045\/045273.html"}},"8":{"nom":"Saint-Denis-En-Val","Listes":{"libelle":"Listes","url":"http:\/\/elections.interieur.gouv.fr\/MN2014\/045\/C1045274.html"},"resultat":{"libelle":"R&eacute;sultats re&ccedil;us 1er tour","url":"http:\/\/elections.interieur.gouv.fr\/MN2014\/045\/045274.html"}},"9":{"nom":"Sainte-Genevi&egrave;ve-Des-Bois","Listes":{"libelle":"Listes","url":"http:\/\/elections.interieur.gouv.fr\/MN2014\/045\/C1045278.html"},"resultat":{"libelle":"R&eacute;sultats re&ccedil;us 1er tour","url":"http:\/\/elections.interieur.gouv.fr\/MN2014\/045\/045278.html"}},"10":{"nom":"Saint-Firmin-Des-Bois","Listes":{"libelle":"Candidats (Scrutin majoritaire)","url":"http:\/\/elections.interieur.gouv.fr\/MN2014\/045\/C1045275.html"},"resultat":{"libelle":"R&eacute;sultats re&ccedil;us 1er tour","url":"http:\/\/elections.interieur.gouv.fr\/MN2014\/045\/045275.html"}},"11":{"nom":"Saint-Firmin-Sur-Loire","Listes":{"libelle":"Candidats (Scrutin majoritaire)","url":"http:\/\/elections.interieur.gouv.fr\/MN2014\/045\/C1045276.html"},"resultat":{"libelle":"R&eacute;sultats re&ccedil;us 1er tour","url":"http:\/\/elections.interieur.gouv.fr\/MN2014\/045\/045276.html"}},"12":{"nom":"Saint-Florent","Listes":{"libelle":"Candidats (Scrutin majoritaire)","url":"http:\/\/elections.interieur.gouv.fr\/MN2014\/045\/C1045277.html"},"resultat":{"libelle":"R&eacute;sultats re&ccedil;us 1er tour","url":"http:\/\/elections.interieur.gouv.fr\/MN2014\/045\/045277.html"}},"13":{"nom":"Saint-Germain-Des-Pr&eacute;s","Listes":{"libelle":"Listes","url":"http:\/\/elections.interieur.gouv.fr\/MN2014\/045\/C1045279.html"},"resultat":{"libelle":"R&eacute;sultats re&ccedil;us 1er tour","url":"http:\/\/elections.interieur.gouv.fr\/MN2014\/045\/045279.html"}},"14":{"nom":"Saint-Gondon","Listes":{"libelle":"Listes","url":"http:\/\/elections.interieur.gouv.fr\/MN2014\/045\/C1045280.html"},"resultat":{"libelle":"R&eacute;sultats re&ccedil;us 1er tour","url":"http:\/\/elections.interieur.gouv.fr\/MN2014\/045\/045280.html"}},"15":{"nom":"Saint-Hilaire-Les-Andr&eacute;sis","Listes":{"libelle":"Candidats (Scrutin majoritaire)","url":"http:\/\/elections.interieur.gouv.fr\/MN2014\/045\/C1045281.html"},"resultat":{"libelle":"R&eacute;sultats re&ccedil;us 1er tour","url":"http:\/\/elections.interieur.gouv.fr\/MN2014\/045\/045281.html"}},"16":{"nom":"Saint-Hilaire-Saint-Mesmin","Listes":{"libelle":"Listes","url":"http:\/\/elections.interieur.gouv.fr\/MN2014\/045\/C1045282.html"},"resultat":{"libelle":"R&eacute;sultats re&ccedil;us 1er tour","url":"http:\/\/elections.interieur.gouv.fr\/MN2014\/045\/045282.html"}},"17":{"nom":"Saint-Hilaire-Sur-Puiseaux","Listes":{"libelle":"Candidats (Scrutin majoritaire)","url":"http:\/\/elections.interieur.gouv.fr\/MN2014\/045\/C1045283.html"},"resultat":{"libelle":"R&eacute;sultats re&ccedil;us 1er tour","url":"http:\/\/elections.interieur.gouv.fr\/MN2014\/045\/045283.html"}},"18":{"nom":"Saint-Jean-De-Braye","Listes":{"libelle":"Listes","url":"http:\/\/elections.interieur.gouv.fr\/MN2014\/045\/C1045284.html"},"resultat":{"libelle":"R&eacute;sultats re&ccedil;us 1er tour","url":"http:\/\/elections.interieur.gouv.fr\/MN2014\/045\/045284.html"}},"19":{"nom":"Saint-Jean-De-La-Ruelle","Listes":{"libelle":"Listes","url":"http:\/\/elections.interieur.gouv.fr\/MN2014\/045\/C1045285.html"},"resultat":{"libelle":"R&eacute;sultats re&ccedil;us 1er tour","url":"http:\/\/elections.interieur.gouv.fr\/MN2014\/045\/045285.html"}},"20":{"nom":"Saint-Jean-Le-Blanc","Listes":{"libelle":"Listes","url":"http:\/\/elections.interieur.gouv.fr\/MN2014\/045\/C1045286.html"},"resultat":{"libelle":"R&eacute;sultats re&ccedil;us 1er tour","url":"http:\/\/elections.interieur.gouv.fr\/MN2014\/045\/045286.html"}},"21":{"nom":"Saint-Loup-De-Gonois","Listes":{"libelle":"Candidats (Scrutin majoritaire)","url":"http:\/\/elections.interieur.gouv.fr\/MN2014\/045\/C1045287.html"},"resultat":{"libelle":"R&eacute;sultats re&ccedil;us 1er tour","url":"http:\/\/elections.interieur.gouv.fr\/MN2014\/045\/045287.html"}},"22":{"nom":"Saint-Loup-Des-Vignes","Listes":{"libelle":"Candidats (Scrutin majoritaire)","url":"http:\/\/elections.interieur.gouv.fr\/MN2014\/045\/C1045288.html"},"resultat":{"libelle":"R&eacute;sultats re&ccedil;us 1er tour","url":"http:\/\/elections.interieur.gouv.fr\/MN2014\/045\/045288.html"}},"23":{"nom":"Saint-Ly&eacute;-La-For&ecirc;t","Listes":{"libelle":"Listes","url":"http:\/\/elections.interieur.gouv.fr\/MN2014\/045\/C1045289.html"},"resultat":{"libelle":"R&eacute;sultats re&ccedil;us 1er tour","url":"http:\/\/elections.interieur.gouv.fr\/MN2014\/045\/045289.html"}},"24":{"nom":"Saint-Martin-D'Abbat","Listes":{"libelle":"Listes","url":"http:\/\/elections.interieur.gouv.fr\/MN2014\/045\/C1045290.html"},"resultat":{"libelle":"R&eacute;sultats re&ccedil;us 1er tour","url":"http:\/\/elections.interieur.gouv.fr\/MN2014\/045\/045290.html"}},"25":{"nom":"Saint-Martin-Sur-Ocre","Listes":{"libelle":"Listes","url":"http:\/\/elections.interieur.gouv.fr\/MN2014\/045\/C1045291.html"},"resultat":{"libelle":"R&eacute;sultats re&ccedil;us 1er tour","url":"http:\/\/elections.interieur.gouv.fr\/MN2014\/045\/045291.html"}},"26":{"nom":"Saint-Maurice-Sur-Aveyron","Listes":{"libelle":"Candidats (Scrutin majoritaire)","url":"http:\/\/elections.interieur.gouv.fr\/MN2014\/045\/C1045292.html"},"resultat":{"libelle":"R&eacute;sultats re&ccedil;us 1er tour","url":"http:\/\/elections.interieur.gouv.fr\/MN2014\/045\/045292.html"}},"27":{"nom":"Saint-Maurice-Sur-Fessard","Listes":{"libelle":"Listes","url":"http:\/\/elections.interieur.gouv.fr\/MN2014\/045\/C1045293.html"},"resultat":{"libelle":"R&eacute;sultats re&ccedil;us 1er tour","url":"http:\/\/elections.interieur.gouv.fr\/MN2014\/045\/045293.html"}},"28":{"nom":"Saint-Michel","Listes":{"libelle":"Candidats (Scrutin majoritaire)","url":"http:\/\/elections.interieur.gouv.fr\/MN2014\/045\/C1045294.html"},"resultat":{"libelle":"R&eacute;sultats re&ccedil;us 1er tour","url":"http:\/\/elections.interieur.gouv.fr\/MN2014\/045\/045294.html"}},"29":{"nom":"Saint-P&eacute;ravy-La-Colombe","Listes":{"libelle":"Candidats (Scrutin majoritaire)","url":"http:\/\/elections.interieur.gouv.fr\/MN2014\/045\/C1045296.html"},"resultat":{"libelle":"R&eacute;sultats re&ccedil;us 1er tour","url":"http:\/\/elections.interieur.gouv.fr\/MN2014\/045\/045296.html"}},"30":{"nom":"Saint-P&egrave;re-Sur-Loire","Listes":{"libelle":"Listes","url":"http:\/\/elections.interieur.gouv.fr\/MN2014\/045\/C1045297.html"},"resultat":{"libelle":"R&eacute;sultats re&ccedil;us 1er tour","url":"http:\/\/elections.interieur.gouv.fr\/MN2014\/045\/045297.html"}},"31":{"nom":"Saint-Pryv&eacute;-Saint-Mesmin","Listes":{"libelle":"Listes","url":"http:\/\/elections.interieur.gouv.fr\/MN2014\/045\/C1045298.html"},"resultat":{"libelle":"R&eacute;sultats re&ccedil;us 1er tour","url":"http:\/\/elections.interieur.gouv.fr\/MN2014\/045\/045298.html"}},"32":{"nom":"Saint-Sigismond","Listes":{"libelle":"Candidats (Scrutin majoritaire)","url":"http:\/\/elections.interieur.gouv.fr\/MN2014\/045\/C1045299.html"},"resultat":{"libelle":"R&eacute;sultats re&ccedil;us 1er tour","url":"http:\/\/elections.interieur.gouv.fr\/MN2014\/045\/045299.html"}},"33":{"nom":"Sandillon","Listes":{"libelle":"Listes","url":"http:\/\/elections.interieur.gouv.fr\/MN2014\/045\/C1045300.html"},"resultat":{"libelle":"R&eacute;sultats re&ccedil;us 1er tour","url":"http:\/\/elections.interieur.gouv.fr\/MN2014\/045\/045300.html"}},"34":{"nom":"Santeau","Listes":{"libelle":"Candidats (Scrutin majoritaire)","url":"http:\/\/elections.interieur.gouv.fr\/MN2014\/045\/C1045301.html"},"resultat":{"libelle":"R&eacute;sultats re&ccedil;us 1er tour","url":"http:\/\/elections.interieur.gouv.fr\/MN2014\/045\/045301.html"}},"35":{"nom":"Saran","Listes":{"libelle":"Listes","url":"http:\/\/elections.interieur.gouv.fr\/MN2014\/045\/C1045302.html"},"resultat":{"libelle":"R&eacute;sultats re&ccedil;us 1er tour","url":"http:\/\/elections.interieur.gouv.fr\/MN2014\/045\/045302.html"}},"36":{"nom":"Sceaux-Du-G&acirc;tinais","Listes":{"libelle":"Candidats (Scrutin majoritaire)","url":"http:\/\/elections.interieur.gouv.fr\/MN2014\/045\/C1045303.html"},"resultat":{"libelle":"R&eacute;sultats re&ccedil;us 1er tour","url":"http:\/\/elections.interieur.gouv.fr\/MN2014\/045\/045303.html"}},"37":{"nom":"Seichebri&egrave;res","Listes":{"libelle":"Candidats (Scrutin majoritaire)","url":"http:\/\/elections.interieur.gouv.fr\/MN2014\/045\/C1045305.html"},"resultat":{"libelle":"R&eacute;sultats re&ccedil;us 1er tour","url":"http:\/\/elections.interieur.gouv.fr\/MN2014\/045\/045305.html"}},"38":{"nom":"Semoy","Listes":{"libelle":"Listes","url":"http:\/\/elections.interieur.gouv.fr\/MN2014\/045\/C1045308.html"},"resultat":{"libelle":"R&eacute;sultats re&ccedil;us 1er tour","url":"http:\/\/elections.interieur.gouv.fr\/MN2014\/045\/045308.html"}},"39":{"nom":"Sennely","Listes":{"libelle":"Candidats (Scrutin majoritaire)","url":"http:\/\/elections.interieur.gouv.fr\/MN2014\/045\/C1045309.html"},"resultat":{"libelle":"R&eacute;sultats re&ccedil;us 1er tour","url":"http:\/\/elections.interieur.gouv.fr\/MN2014\/045\/045309.html"}},"40":{"nom":"Sermaises","Listes":{"libelle":"Listes","url":"http:\/\/elections.interieur.gouv.fr\/MN2014\/045\/C1045310.html"},"resultat":{"libelle":"R&eacute;sultats re&ccedil;us 1er tour","url":"http:\/\/elections.interieur.gouv.fr\/MN2014\/045\/045310.html"}},"41":{"nom":"Sigloy","Listes":{"libelle":"Candidats (Scrutin majoritaire)","url":"http:\/\/elections.interieur.gouv.fr\/MN2014\/045\/C1045311.html"},"resultat":{"libelle":"R&eacute;sultats re&ccedil;us 1er tour","url":"http:\/\/elections.interieur.gouv.fr\/MN2014\/045\/045311.html"}},"42":{"nom":"Solterre","Listes":{"libelle":"Candidats (Scrutin majoritaire)","url":"http:\/\/elections.interieur.gouv.fr\/MN2014\/045\/C1045312.html"},"resultat":{"libelle":"R&eacute;sultats re&ccedil;us 1er tour","url":"http:\/\/elections.interieur.gouv.fr\/MN2014\/045\/045312.html"}},"43":{"nom":"Sougy","Listes":{"libelle":"Candidats (Scrutin majoritaire)","url":"http:\/\/elections.interieur.gouv.fr\/MN2014\/045\/C1045313.html"},"resultat":{"libelle":"R&eacute;sultats re&ccedil;us 1er tour","url":"http:\/\/elections.interieur.gouv.fr\/MN2014\/045\/045313.html"}},"44":{"nom":"Sully-La-Chapelle","Listes":{"libelle":"Candidats (Scrutin majoritaire)","url":"http:\/\/elections.interieur.gouv.fr\/MN2014\/045\/C1045314.html"},"resultat":{"libelle":"R&eacute;sultats re&ccedil;us 1er tour","url":"http:\/\/elections.interieur.gouv.fr\/MN2014\/045\/045314.html"}},"45":{"nom":"Sully-Sur-Loire","Listes":{"libelle":"Listes","url":"http:\/\/elections.interieur.gouv.fr\/MN2014\/045\/C1045315.html"},"resultat":{"libelle":"R&eacute;sultats re&ccedil;us 1er tour","url":"http:\/\/elections.interieur.gouv.fr\/MN2014\/045\/045315.html"}},"46":{"nom":"Sury-Aux-Bois","Listes":{"libelle":"Candidats (Scrutin majoritaire)","url":"http:\/\/elections.interieur.gouv.fr\/MN2014\/045\/C1045316.html"},"resultat":{"libelle":"R&eacute;sultats re&ccedil;us 1er tour","url":"http:\/\/elections.interieur.gouv.fr\/MN2014\/045\/045316.html"}}}},"19":{"url":"http:\/\/elections.interieur.gouv.fr\/MN2014\/045\/045T.html","libelle":"T","villes":{"1":{"nom":"Tavers","Listes":{"libelle":"Listes","url":"http:\/\/elections.interieur.gouv.fr\/MN2014\/045\/C1045317.html"},"resultat":{"libelle":"R&eacute;sultats re&ccedil;us 1er tour","url":"http:\/\/elections.interieur.gouv.fr\/MN2014\/045\/045317.html"}},"2":{"nom":"Thignonville","Listes":{"libelle":"Candidats (Scrutin majoritaire)","url":"http:\/\/elections.interieur.gouv.fr\/MN2014\/045\/C1045320.html"},"resultat":{"libelle":"R&eacute;sultats re&ccedil;us 1er tour","url":"http:\/\/elections.interieur.gouv.fr\/MN2014\/045\/045320.html"}},"3":{"nom":"Thimory","Listes":{"libelle":"Candidats (Scrutin majoritaire)","url":"http:\/\/elections.interieur.gouv.fr\/MN2014\/045\/C1045321.html"},"resultat":{"libelle":"R&eacute;sultats re&ccedil;us 1er tour","url":"http:\/\/elections.interieur.gouv.fr\/MN2014\/045\/045321.html"}},"4":{"nom":"Thorailles","Listes":{"libelle":"Candidats (Scrutin majoritaire)","url":"http:\/\/elections.interieur.gouv.fr\/MN2014\/045\/C1045322.html"},"resultat":{"libelle":"R&eacute;sultats re&ccedil;us 1er tour","url":"http:\/\/elections.interieur.gouv.fr\/MN2014\/045\/045322.html"}},"5":{"nom":"Thou","Listes":{"libelle":"Candidats (Scrutin majoritaire)","url":"http:\/\/elections.interieur.gouv.fr\/MN2014\/045\/C1045323.html"},"resultat":{"libelle":"R&eacute;sultats re&ccedil;us 1er tour","url":"http:\/\/elections.interieur.gouv.fr\/MN2014\/045\/045323.html"}},"6":{"nom":"Tigy","Listes":{"libelle":"Listes","url":"http:\/\/elections.interieur.gouv.fr\/MN2014\/045\/C1045324.html"},"resultat":{"libelle":"R&eacute;sultats re&ccedil;us 1er tour","url":"http:\/\/elections.interieur.gouv.fr\/MN2014\/045\/045324.html"}},"7":{"nom":"Tivernon","Listes":{"libelle":"Candidats (Scrutin majoritaire)","url":"http:\/\/elections.interieur.gouv.fr\/MN2014\/045\/C1045325.html"},"resultat":{"libelle":"R&eacute;sultats re&ccedil;us 1er tour","url":"http:\/\/elections.interieur.gouv.fr\/MN2014\/045\/045325.html"}},"8":{"nom":"Tournoisis","Listes":{"libelle":"Candidats (Scrutin majoritaire)","url":"http:\/\/elections.interieur.gouv.fr\/MN2014\/045\/C1045326.html"},"resultat":{"libelle":"R&eacute;sultats re&ccedil;us 1er tour","url":"http:\/\/elections.interieur.gouv.fr\/MN2014\/045\/045326.html"}},"9":{"nom":"Tra&icirc;nou","Listes":{"libelle":"Listes","url":"http:\/\/elections.interieur.gouv.fr\/MN2014\/045\/C1045327.html"},"resultat":{"libelle":"R&eacute;sultats re&ccedil;us 1er tour","url":"http:\/\/elections.interieur.gouv.fr\/MN2014\/045\/045327.html"}},"10":{"nom":"Treilles-En-G&acirc;tinais","Listes":{"libelle":"Candidats (Scrutin majoritaire)","url":"http:\/\/elections.interieur.gouv.fr\/MN2014\/045\/C1045328.html"},"resultat":{"libelle":"R&eacute;sultats re&ccedil;us 1er tour","url":"http:\/\/elections.interieur.gouv.fr\/MN2014\/045\/045328.html"}},"11":{"nom":"Trigu&egrave;res","Listes":{"libelle":"Listes","url":"http:\/\/elections.interieur.gouv.fr\/MN2014\/045\/C1045329.html"},"resultat":{"libelle":"R&eacute;sultats re&ccedil;us 1er tour","url":"http:\/\/elections.interieur.gouv.fr\/MN2014\/045\/045329.html"}},"12":{"nom":"Trinay","Listes":{"libelle":"Candidats (Scrutin majoritaire)","url":"http:\/\/elections.interieur.gouv.fr\/MN2014\/045\/C1045330.html"},"resultat":{"libelle":"R&eacute;sultats re&ccedil;us 1er tour","url":"http:\/\/elections.interieur.gouv.fr\/MN2014\/045\/045330.html"}}}},"20":{"url":"http:\/\/elections.interieur.gouv.fr\/MN2014\/045\/045V.html","libelle":"V","villes":{"1":{"nom":"Vannes-Sur-Cosson","Listes":{"libelle":"Candidats (Scrutin majoritaire)","url":"http:\/\/elections.interieur.gouv.fr\/MN2014\/045\/C1045331.html"},"resultat":{"libelle":"R&eacute;sultats re&ccedil;us 1er tour","url":"http:\/\/elections.interieur.gouv.fr\/MN2014\/045\/045331.html"}},"2":{"nom":"Varennes-Changy","Listes":{"libelle":"Listes","url":"http:\/\/elections.interieur.gouv.fr\/MN2014\/045\/C1045332.html"},"resultat":{"libelle":"R&eacute;sultats re&ccedil;us 1er tour","url":"http:\/\/elections.interieur.gouv.fr\/MN2014\/045\/045332.html"}},"3":{"nom":"Vennecy","Listes":{"libelle":"Listes","url":"http:\/\/elections.interieur.gouv.fr\/MN2014\/045\/C1045333.html"},"resultat":{"libelle":"R&eacute;sultats re&ccedil;us 1er tour","url":"http:\/\/elections.interieur.gouv.fr\/MN2014\/045\/045333.html"}},"4":{"nom":"Vieilles-Maisons-Sur-Joudry","Listes":{"libelle":"Candidats (Scrutin majoritaire)","url":"http:\/\/elections.interieur.gouv.fr\/MN2014\/045\/C1045334.html"},"resultat":{"libelle":"R&eacute;sultats re&ccedil;us 1er tour","url":"http:\/\/elections.interieur.gouv.fr\/MN2014\/045\/045334.html"}},"5":{"nom":"Vienne-En-Val","Listes":{"libelle":"Listes","url":"http:\/\/elections.interieur.gouv.fr\/MN2014\/045\/C1045335.html"},"resultat":{"libelle":"R&eacute;sultats re&ccedil;us 1er tour","url":"http:\/\/elections.interieur.gouv.fr\/MN2014\/045\/045335.html"}},"6":{"nom":"Viglain","Listes":{"libelle":"Candidats (Scrutin majoritaire)","url":"http:\/\/elections.interieur.gouv.fr\/MN2014\/045\/C1045336.html"},"resultat":{"libelle":"R&eacute;sultats re&ccedil;us 1er tour","url":"http:\/\/elections.interieur.gouv.fr\/MN2014\/045\/045336.html"}},"7":{"nom":"Villamblain","Listes":{"libelle":"Candidats (Scrutin majoritaire)","url":"http:\/\/elections.interieur.gouv.fr\/MN2014\/045\/C1045337.html"},"resultat":{"libelle":"R&eacute;sultats re&ccedil;us 1er tour","url":"http:\/\/elections.interieur.gouv.fr\/MN2014\/045\/045337.html"}},"8":{"nom":"Villemandeur","Listes":{"libelle":"Listes","url":"http:\/\/elections.interieur.gouv.fr\/MN2014\/045\/C1045338.html"},"resultat":{"libelle":"R&eacute;sultats re&ccedil;us 1er tour","url":"http:\/\/elections.interieur.gouv.fr\/MN2014\/045\/045338.html"}},"9":{"nom":"Villemoutiers","Listes":{"libelle":"Candidats (Scrutin majoritaire)","url":"http:\/\/elections.interieur.gouv.fr\/MN2014\/045\/C1045339.html"},"resultat":{"libelle":"R&eacute;sultats re&ccedil;us 1er tour","url":"http:\/\/elections.interieur.gouv.fr\/MN2014\/045\/045339.html"}},"10":{"nom":"Villemurlin","Listes":{"libelle":"Candidats (Scrutin majoritaire)","url":"http:\/\/elections.interieur.gouv.fr\/MN2014\/045\/C1045340.html"},"resultat":{"libelle":"R&eacute;sultats re&ccedil;us 1er tour","url":"http:\/\/elections.interieur.gouv.fr\/MN2014\/045\/045340.html"}},"11":{"nom":"Villeneuve-Sur-Conie","Listes":{"libelle":"Candidats (Scrutin majoritaire)","url":"http:\/\/elections.interieur.gouv.fr\/MN2014\/045\/C1045341.html"},"resultat":{"libelle":"R&eacute;sultats re&ccedil;us 1er tour","url":"http:\/\/elections.interieur.gouv.fr\/MN2014\/045\/045341.html"}},"12":{"nom":"Villereau","Listes":{"libelle":"Candidats (Scrutin majoritaire)","url":"http:\/\/elections.interieur.gouv.fr\/MN2014\/045\/C1045342.html"},"resultat":{"libelle":"R&eacute;sultats re&ccedil;us 1er tour","url":"http:\/\/elections.interieur.gouv.fr\/MN2014\/045\/045342.html"}},"13":{"nom":"Villevoques","Listes":{"libelle":"Candidats (Scrutin majoritaire)","url":"http:\/\/elections.interieur.gouv.fr\/MN2014\/045\/C1045343.html"},"resultat":{"libelle":"R&eacute;sultats re&ccedil;us 1er tour","url":"http:\/\/elections.interieur.gouv.fr\/MN2014\/045\/045343.html"}},"14":{"nom":"Villorceau","Listes":{"libelle":"Listes","url":"http:\/\/elections.interieur.gouv.fr\/MN2014\/045\/C1045344.html"},"resultat":{"libelle":"R&eacute;sultats re&ccedil;us 1er tour","url":"http:\/\/elections.interieur.gouv.fr\/MN2014\/045\/045344.html"}},"15":{"nom":"Vimory","Listes":{"libelle":"Listes","url":"http:\/\/elections.interieur.gouv.fr\/MN2014\/045\/C1045345.html"},"resultat":{"libelle":"R&eacute;sultats re&ccedil;us 1er tour","url":"http:\/\/elections.interieur.gouv.fr\/MN2014\/045\/045345.html"}},"16":{"nom":"Vitry-Aux-Loges","Listes":{"libelle":"Listes","url":"http:\/\/elections.interieur.gouv.fr\/MN2014\/045\/C1045346.html"},"resultat":{"libelle":"R&eacute;sultats re&ccedil;us 1er tour","url":"http:\/\/elections.interieur.gouv.fr\/MN2014\/045\/045346.html"}},"17":{"nom":"Vrigny","Listes":{"libelle":"Candidats (Scrutin majoritaire)","url":"http:\/\/elections.interieur.gouv.fr\/MN2014\/045\/C1045347.html"},"resultat":{"libelle":"R&eacute;sultats re&ccedil;us 1er tour","url":"http:\/\/elections.interieur.gouv.fr\/MN2014\/045\/045347.html"}}}},"21":{"url":"http:\/\/elections.interieur.gouv.fr\/MN2014\/045\/045Y.html","libelle":"Y","villes":{"1":{"nom":"Y&egrave;vre-La-Ville","Listes":{"libelle":"Candidats (Scrutin majoritaire)","url":"http:\/\/elections.interieur.gouv.fr\/MN2014\/045\/C1045348.html"},"resultat":{"libelle":"R&eacute;sultats re&ccedil;us 1er tour","url":"http:\/\/elections.interieur.gouv.fr\/MN2014\/045\/045348.html"}}}}}}}